<?xml version="1.0" encoding="UTF-8"?><i><chatserver>chat.bilibili.com</chatserver><chatid>9706083</chatid><mission>0</mission><maxlimit>3000</maxlimit><state>0</state><real_name>0</real_name><source>k-v</source><d p="5.85000,1,25,16777215,1471975365,0,fcb7b645,2318715825">第一</d><d p="163.78100,1,25,16777215,1471978980,0,3bb4e4c3,2318736459">口水声让人受不了啊</d><d p="15.33500,1,25,16777215,1471979008,0,a3b47842,2318769731">第二</d><d p="124.76600,1,25,16777215,1471979009,0,f69fd2f2,2318770791">说又不说的感觉好好</d><d p="40.40200,1,25,16777215,1471986302,0,186290df,2318843361">这是新的吗 德叔好久不见 </d><d p="28.88600,1,25,16777215,1471993653,0,75f5f970,2318932617">这是德叔新</d><d p="6.40800,1,25,16777215,1472018534,0,3d6b1359,2320453055">前</d><d p="6.08100,1,25,16777215,1472025858,0,72088c31,2321049797">更新冒泡</d><d p="143.07900,1,25,16777215,1472044193,0,33e6f3d9,2322821861">德叔的视频怎么也有底噪了？！搬运的问题？</d><d p="0.74600,1,25,16777215,1472047858,0,d00afe28,2323209887">第一？</d><d p="124.73500,1,25,16777215,1472055146,0,fbae1fb9,2323656795">瘦了，唉</d><d p="11.59800,1,25,16777215,1472144513,0,8f9eded1,2329150525">德叔你终于回来了</d><d p="13.29700,1,25,16777215,1472144514,0,8f9eded1,2329152287">我前几天才跑油管上去关注了德叔。。求他回来 </d><d p="43.43800,1,25,16777215,1472195015,0,b9239376,2332659251">第一次听男性的ASMR</d><d p="69.92300,1,25,16777215,1472195015,0,b9239376,2332661463">ASMR是个深坑(இωஇ )</d><d p="96.31500,5,25,16777215,1472213314,0,b986b5d2,2334206591">放屁</d><d p="107.92500,1,25,16777215,1472220650,0,8ae2ac8a,2335044515">好听</d><d p="107.03900,1,25,16777215,1472281412,0,ea494122,2338206139">哈哈哈哈</d><d p="203.47600,1,25,16777215,1472317276,0,2286b36d,2341395083">前面那个说搬运问题的那个能不能憋这么无知</d><d p="104.52800,1,25,16777215,1472317317,0,c070a39b,2341504709">要听弯了！！</d><d p="56.43200,1,25,16777215,1472320948,0,9ff70686,2341568393">ASMR千千万，德叔e叔最好看</d><d p="112.95000,1,25,16777215,1472386099,0,a25f126f,2345518397">零底噪</d><d p="130.20700,1,25,16777215,1472393424,0,30731a47,2346216223">气泡音~</d><d p="202.63200,1,25,16777215,1472393425,0,30731a47,2346223095">困困困！！</d><d p="79.69000,1,25,16777215,1472397063,0,fa665e2b,2346450653">SM ➕ AR ＝asmr （手动滑稽）</d><d p="156.98800,1,25,16777215,1472446912,0,774470ad,2348765307">迷途有</d><d p="205.61200,1,25,16777215,1472483505,0,9290f4fa,2351902021">明明没底噪啊</d><d p="146.52100,1,25,16777215,1472487125,0,2b9b3b1b,2351999951">为啥我感觉这种有话说不出的感觉好难受qwq</d><d p="182.33100,1,25,16777215,1472487173,0,d5d636c9,2352172879">耳机福利</d><d p="213.99300,1,25,16777215,1472487174,0,d5d636c9,2352174783">好好玩</d><d p="80.52700,1,25,16777215,1472493720,0,a8348a8,2352337451">～真的见叔困shjsjdjdjjdjj</d><d p="159.41600,1,25,16777215,1472515731,0,92cf316e,2352766787">他说一句我起一层鸡皮疙瘩</d><d p="10.97900,1,25,16777215,1472569902,0,84e89bd9,2356708591">额</d><d p="104.24600,1,25,16777215,1472569904,0,84e89bd9,2356714677">听不懂。。。</d><d p="137.24600,1,25,16777215,1472569904,0,84e89bd9,2356716881">后面那个画。。</d><d p="13.45400,1,25,16777215,1472573524,0,30731a47,2356791631">要睡了。。</d><d p="43.60200,1,25,16777215,1472576513,0,5252d88b,2357083603">起鸡皮……</d><d p="102.51300,1,25,16777215,1472580136,0,3d0976fb,2357119967">哈哈哈哈哈哈哈前面弹幕 这叫我怎么睡觉啊哈哈哈哈</d><d p="111.54800,1,25,16777215,1472587450,0,df26acda,2357230885">好像德叔就在我耳边果然还是应该用好耳机</d><d p="173.59200,1,25,41194,1472587451,0,df26acda,2357231707">感觉快化了</d><d p="130.38200,1,25,16777215,1472613067,0,e756641,2357868135">感觉要搞基了</d><d p="49.59200,1,25,16777215,1472627029,0,b66eff60,2358955271">腰好痒</d><d p="27.49100,1,25,16777215,1472659957,0,8bbdb6ad,2360992309">写了哈？</d><d p="68.93900,4,25,16777215,1472659958,0,8bbdb6ad,2360995339">我靠，这你都能看出来？？！</d><d p="141.92000,4,25,16777215,1472659960,0,8bbdb6ad,2360999957">不用想了。那就是我变的</d><d p="63.96100,1,25,16777215,1472659968,0,cc834cbe,2361016087">完全看不懂写了什么...</d><d p="28.62900,4,25,16777215,1472662898,0,816ce426,2361110491">Sounds</d><d p="52.44100,4,25,41194,1472746347,0,4a27ed3b,2364067003">very quite</d><d p="130.19800,4,25,41194,1472746350,0,4a27ed3b,2364073317">"talke" to me</d><d p="73.88400,1,25,16777215,1472749317,0,73f8f6c1,2364242577">卡巴卡巴</d><d p="1072.05000,1,25,16777215,1472796124,0,2714cff4,2365264409">bā</d><d p="78.25900,4,25,16777215,1472796141,0,c1459a5c,2365305819">快速触发音</d><d p="193.79800,1,25,16777215,1472829112,0,2a8780b7,2367375285">困了</d><d p="198.84400,1,25,16777215,1472829113,0,2a8780b7,2367376165">困</d><d p="349.55800,1,25,16777215,1472829116,0,2a8780b7,2367386937">有多少人坚持到现在</d><d p="73.46700,1,25,16777215,1472832763,0,ee116d79,2367546943">马大姐的也不错啊！</d><d p="101.05300,1,25,16777215,1472886223,0,e73b33ff,2369546331">23333333</d><d p="161.66200,1,25,16777215,1472908166,0,457ce73b,2371036909">呼吸好爽</d><d p="99.10200,1,25,16777215,1472911831,0,89245f1b,2371414369">眼看德叔这头发要完</d><d p="52.01200,1,25,15138834,1472919122,0,a31f5437,2371876315">有没有觉得德叔很像守望者里的一个人物？</d><d p="103.00300,1,25,15138834,1472919123,0,a31f5437,2371880965">守望者里的罗杰</d><d p="192.91100,1,25,15138834,1472919125,0,a31f5437,2371888309">这里有多少妹纸？</d><d p="119.58200,1,25,16777215,1472919126,0,8050c641,2371891999">要听底躁把声音开到最大</d><d p="53.66100,1,25,16777215,1472919177,0,41f16390,2372069449">quiet 和quite 都分不清。。。。底下蓝字</d><d p="65.15300,1,25,16777215,1472922098,0,15a3724d,2372170579">徳叔有点像76</d><d p="109.90500,1,25,16777215,1472922115,0,30cdf7e4,2372205139">26333333</d><d p="20.14200,1,25,16777215,1472929382,0,b4c6e36d,2372302221">摩擦音受不了 撤离</d><d p="46.50600,1,25,16777215,1472994582,0,f52d50db,2375561237">久违的痒。。。。</d><d p="53.62800,1,25,16777215,1473005524,0,21e80ad1,2376077311">两边没有装隔音棉，就有那么点低噪了</d><d p="10.81800,1,25,16777215,1473066345,0,391f9a83,2377589793">底噪感人…</d><d p="120.73900,1,25,16777215,1473084618,0,73331853,2378499395">男的asmr我只服德叔</d><d p="191.87100,1,25,16777215,1473084631,0,60b8e123,2378545761">德叔英文名是啥</d><d p="110.01700,1,25,16777215,1473167354,0,c68ce089,2380967811">放屁to you的你别跑</d><d p="59.87100,1,25,16777215,1473257401,0,86eb4786,2383650753">不敢想象50年后的vr,mr什么样</d><d p="337.49000,1,25,16777215,1473257406,0,86eb4786,2383666829">要是女的看着我就好了</d><d p="172.77700,1,25,16777215,1473261103,0,b08a8f8,2383988167">简直太痒了</d><d p="299.73200,1,25,16777215,1473264747,0,b8de6c6a,2384099843">亲爱宝贝？</d><d p="113.93600,1,25,16777215,1473264770,0,93850224,2384145513">我水显了</d><d p="102.70000,1,25,16777215,1473267669,0,e1cc179a,2384175637">哈哈哈前面放屁的别走！2333</d><d p="106.02200,1,25,16777215,1473310867,0,387b195f,2384865131">蜜汁羞耻</d><d p="350.19300,1,25,16777215,1473329211,0,f5626b3d,2385545829">-------------</d><d p="20.91900,1,25,16777215,1473426567,0,86eb4786,2388842275">然而我上不油管</d><d p="92.04300,5,25,16777215,1473433896,0,60060e8f,2389378417">放屁tuyou……笑的我睡意全无</d><d p="118.69900,1,25,16707842,1473491014,0,84291a00,2391339365">红红火火恍恍惚惚</d><d p="152.69400,1,25,16777215,1473520265,0,9bf12f8c,2393225383">难受可以不看，千万人德叔最牛逼</d><d p="272.88000,1,25,16777215,1473520268,0,9bf12f8c,2393241137">为人了</d><d p="356.28600,1,25,16777215,1473520271,0,9bf12f8c,2393254551">～</d><d p="234.10100,1,25,16777215,1473530549,0,3efee60,2393820589">这个德叔一直在那舞乍啥呢，我有点没看懂</d><d p="72.66300,1,25,16777215,1473573742,0,76a011d0,2395323013">弹幕迟早可以脑补成H片…</d><d p="102.64300,1,25,16777215,1473573743,0,76a011d0,2395324927">真心考听力…只听到口水</d><d p="285.23800,1,25,16777215,1473685764,0,457ce73b,2399545609">很可以</d><d p="180.72200,1,25,16777215,1473789756,0,b7c82185,2403164009">就喜欢口水声</d><d p="199.62500,1,25,16777215,1473789756,0,b7c82185,2403164293">超爱</d><d p="267.77200,1,25,16777215,1473822681,0,812a3b35,2403584357">都睡了吗</d><d p="127.90000,1,25,16777215,1473898120,0,18fb3bff,2407030749">德叔不能有底躁！</d><d p="64.06700,1,25,16777215,1473955927,0,28015e6c,2410987355">76?</d><d p="357.77400,1,25,16777215,1474042321,0,a98ec0a9,2415920597">有</d><d p="14.39600,1,25,16777215,1474048957,0,f622d040,2416344963">神神叨叨德</d><d p="31.41700,1,25,16777215,1474048957,0,f622d040,2416345425">见德困</d><d p="195.39400,5,25,16777215,1474081898,0,59c6399f,2417210105">Dmitri</d><d p="67.52900,1,25,16707842,1474095834,0,2fde3cc9,2418305117">头皮痒</d><d p="110.07300,1,25,16777215,1474283261,0,b397206b,2425003585">放屁是什么鬼</d><d p="326.63100,1,25,16777215,1474311788,0,b7c296b,2426062855">德叔娇喘福利</d><d p="204.54200,1,25,16777215,1474380621,0,57cd5e17,2428131237">老司机觉得这段轻语很舒服</d><d p="116.64000,1,25,16777215,1474390896,0,4ffaedb8,2428646297">關彈幕保睡意</d><d p="129.65900,1,25,16777215,1474401865,0,368cec,2428764051">只能听见口水声</d><d p="31.11300,1,25,16777215,1474467057,0,86eb4786,2430785851">从油管下视频是不是很费钱的……</d><d p="116.94800,1,25,16777215,1474474354,0,be7509d1,2431062493">可以可以，</d><d p="179.35100,1,25,16777215,1474474355,0,be7509d1,2431064667">好大的喘气声，</d><d p="55.59700,1,25,16777215,1474477292,0,82925e07,2431154465">你只需要一个免费的VPN</d><d p="87.76900,1,25,16777215,1474553410,0,8b707192,2433129835">，</d><d p="61.59700,1,25,16777215,1474603945,0,d6c86869,2434233089">有野生字幕君就很开心啦，字幕君加油哦</d><d p="91.99800,1,25,16777215,1474603946,0,d6c86869,2434234837">并听不清，求字幕君</d><d p="329.95400,1,25,41194,1474675706,0,e260a97,2437005847">这真的不是打呼噜哦？</d><d p="353.89300,1,25,41194,1474675706,0,e260a97,2437006609">我</d><d p="103.42600,1,25,14811775,1474726249,0,1eba354c,2440211601">德式做法</d><d p="7.15300,1,25,16777215,1474783349,0,b25c8e28,2442562007">来了来了！！！！！！1</d><d p="98.76500,1,25,16777215,1474787020,0,ea8843c1,2442839067">简述困</d><d p="204.08300,1,25,16777215,1474812609,0,2ec7838b,2444278339">千万人中德叔最6</d><d p="534.83100,1,25,16777215,1474822918,0,2fe40ffc,2444927815">捧臭脚</d><d p="15.24100,1,25,16777215,1474822919,0,2fe40ffc,2444929123">捧臭脚</d><d p="121.88700,1,25,16777215,1474830198,0,d5fdd435,2444997107">大半夜笑出声</d><d p="1091.32000,1,25,16777215,1474837541,0,59f081a0,2445064837">f’</d><d p="273.79300,1,25,16777215,1474869734,0,9d41420c,2445735005">嗯，睡了</d><d p="76.12100,1,25,16777215,1474902667,0,eaf2a3c1,2447146669">像罗夏的憋跑！</d><d p="70.47100,1,25,16777215,1474902716,0,53025405,2447308389">76+1</d><d p="137.34700,1,25,16777215,1474906320,0,ccb8d59a,2447319341">放屁什么的不要睡觉了。。。</d><d p="269.38700,1,25,16777215,1474956173,0,cb22d84c,2448785545">放屁to you</d><d p="57.44800,1,25,16777215,1474989086,0,71dc4778,2450267393">德叔有毒！我已经开始困了</d><d p="361.89400,1,25,16777215,1475082116,0,59fc5d67,2457904953">1</d><d p="811.42800,1,25,16777215,1475158247,0,d6a62175,2461855769">g</d><d p="85.68800,1,25,16777215,1475211675,0,fd0906d9,2465331405">太哲学了，听不懂</d><d p="210.45400,1,25,16777215,1475222667,0,4692f99c,2467667733">总感觉他手在我胸口摸。。。</d><d p="359.80100,1,25,16777215,1475248278,0,274dbb6,2469717145">我</d><d p="207.13000,1,25,16777215,1475254907,0,8f6384cf,2470166323">我觉得自己好变态</d><d p="204.98500,1,25,16777215,1475384504,0,efb0a1fd,2483883037">德叔原名德玛西亚</d><d p="70.79700,5,25,16777215,1475410129,0,20767a9a,2488507249">德叔比划了半天是说，be quiet，no sounds</d><d p="104.00000,1,25,16777215,1475424729,0,99af7eed,2489806285">噗</d><d p="405.99300,1,25,16777215,1475427708,0,3dc5b6d6,2490130445">dmitri</d><d p="171.54800,1,25,16777215,1475427712,0,3dc5b6d6,2490137033">好爽</d><d p="243.97500,1,25,16777215,1475427713,0,3dc5b6d6,2490139579">dmitir 德叔英文名</d><d p="283.46800,1,25,16777215,1475467943,0,e0516ed8,2491334819">睡前发条弹幕</d><d p="100.09100,1,25,16777215,1475500144,0,c067578d,2496161395">什么鬼</d><d p="297.67500,1,25,16777215,1475514081,0,944146ec,2497539249">他不说话就好了</d><d p="94.50600,1,25,16777215,1475517751,0,46548a3b,2497683065">口水音太重啦</d><d p="107.69400,1,25,16777215,1475593869,0,63c94012,2503152193">被弹幕笑醒</d><d p="303.22700,1,25,16777215,1475593901,0,5cd88020,2503327673">感到窒息</d><d p="47.65500,1,25,16777215,1475626117,0,f5270d28,2504301255">表白字幕君</d><d p="59.99600,1,25,16777215,1475647354,0,c2c1bfc4,2505958839">罗夏</d><d p="88.71600,1,25,16777215,1475647354,0,c2c1bfc4,2505961517">没跑</d><d p="229.06600,1,25,16777215,1475676659,0,8e75d6f,2508784549">搬运的那个笑死了</d><d p="107.26700,5,25,16707842,1475686872,0,a0a6c37a,2509428529">不让人睡了hhhh</d><d p="183.42800,1,25,16777215,1475752028,0,7774c53d,2512865403">不不不，我真的感觉有人往我耳朵里吹气</d><d p="107.78500,1,25,16777215,1475759373,0,e7c287fe,2513773203">23333333放屁的别走</d><d p="137.05700,1,25,16777215,1475816487,0,c3caa2f4,2516625645">为什么我困了，但是还笑起来了</d><d p="154.32000,1,25,16777215,1475838459,0,b1a44932,2518310309">我想发个弹幕</d><d p="40.18500,1,25,16777215,1475853096,0,6a257983,2519398967">做的什么法</d><d p="252.56300,1,25,16777215,1475856759,0,32794f3c,2519611695">ditmari不是侠盗猎车的？</d><d p="152.64300,1,25,16777215,1475982664,0,4c1afb89,2536132983">qwq</d><d p="68.86100,1,25,16777215,1476029522,0,58dc559c,2539176735">腰好痒23333</d><d p="117.33300,1,25,16777215,1476029522,0,58dc559c,2539179211">放屁to you23333</d><d p="205.63500,1,25,16777215,1476065406,0,4ccfb07,2539673367">看的都是妹子吧</d><d p="114.97600,1,25,16777215,1476112282,0,593ee184,2541993469">听了好多次了，想睡觉就听</d><d p="527.54400,1,25,16777215,1476288743,0,733f93cf,2548032205">徳叔是催眠师么？？？？</d><d p="146.13300,1,25,16777215,1476385387,0,8ee42072,2550953623">知道熊叔的这么少吗</d><d p="69.47300,1,25,16777215,1476432298,0,d8d92284,2552076041">牛啊</d><d p="77.08200,4,25,16777215,1476446913,0,4a27ed3b,2552831763">just a little bit of energy</d><d p="101.06600,4,25,16777215,1476446915,0,4a27ed3b,2552837481">just a little bit of time</d><d p="129.46100,4,25,16777215,1476446916,0,4a27ed3b,2552842087">tell me, something different</d><d p="135.72100,4,25,16777215,1476446917,0,4a27ed3b,2552846347">something different(?)</d><d p="199.94100,4,25,16777215,1476446920,0,4a27ed3b,2552860659">so just clear energy</d><d p="78.89000,1,25,16777215,1476461567,0,b7b1faf3,2553825159">除了德叔，不听其他男性asmr</d><d p="85.56800,1,25,16777215,1476550881,0,aa97118e,2557991775">啊啊啊</d><d p="357.29500,1,25,16777215,1476717104,0,8bcb75db,2564313255">在</d><d p="144.67300,1,25,16777215,1476889879,0,a94eaedf,2571661013">好困</d><d p="31.49400,1,25,16777215,1476954336,0,cc21636d,2573510335">好喜欢德叔的asmr啊！</d><d p="45.03100,1,25,16777215,1477059017,0,f245e9c1,2578222591">好想知道德叔的配置</d><d p="74.00000,1,25,16777215,1477059039,0,9e8c02b1,2578331297">我不行了，我后腰痒痒的厉害！</d><d p="106.77000,1,25,16777215,1477066377,0,2560894,2578860645">睡意全无</d><d p="135.29900,1,25,16777215,1477066377,0,2560894,2578861805">本来差点睡了的</d><d p="378.58400,1,25,16777215,1477112482,0,de79743d,2580142967">啊！干嘛抓我胸！</d><d p="452.28400,1,25,16777215,1477112484,0,de79743d,2580152825">come on！跟我来吧！把你的灵魂交给我吧！</d><d p="43.81200,1,25,16777215,1477202533,0,13c83d73,2584448681">么么哒！</d><d p="286.33100,1,25,16777215,1477228189,0,f6747ce8,2586255497">好痒啊背后</d><d p="363.51300,1,25,16777215,1477228190,0,f6747ce8,2586260945">我</d><d p="106.90400,1,25,16777215,1477231827,0,25cb26d7,2586412631">叔的头发吃枣…</d><d p="14.98300,1,25,16777215,1477235514,0,2b7bb8b3,2586736455">20161023</d><d p="298.14300,1,25,15138834,1477321902,0,d496c351,2591386665">撑不住了 晚安</d><d p="28.46800,4,25,16707842,1477397335,0,3a88c036,2594110925">赛药丝</d><d p="39.22100,4,25,16707842,1477397336,0,3a88c036,2594112811">服药目！</d><d p="46.08800,1,25,16777215,1477397337,0,3a88c036,2594115743">麦药桑！</d><d p="44.65700,1,25,16777215,1477397337,0,3a88c036,2594117403">买药桑！</d><d p="49.39300,1,25,16777215,1477397338,0,3a88c036,2594118825">快儿！！</d><d p="18.27300,1,25,16777215,1477404646,0,2b7bb8b3,2594825209">20161025</d><d p="359.60600,1,25,16777215,1477411954,0,bd585937,2595149893">我</d><d p="389.16800,1,25,16777215,1477411956,0,bd585937,2595153133">放屁to you</d><d p="538.33400,1,25,16777215,1477411959,0,bd585937,2595159145">有可能，感觉他挺专业的</d><d p="362.57900,1,25,16777215,1477483737,0,53ab2a82,2598992529">我</d><d p="95.90700,4,25,16777215,1477685089,0,834b4557,2606852187">放屁</d><d p="222.63200,1,25,16777215,1477915701,0,25cb26d7,2618521713">⬅️前面把ASMR和gay混淆概念也太失礼了…</d><d p="249.93900,1,25,16777215,1477915702,0,25cb26d7,2618524437">ASMR到现在已经这么长时间了…怎么还有那么多小白</d><d p="262.29200,1,25,16777215,1477915702,0,25cb26d7,2618525563">前面那个节奏大师好可怕</d><d p="153.97800,1,25,16777215,1478099488,0,ac210dee,2625629709">熊叔不是做实验的？你在这里是屁用</d><d p="64.29400,1,25,16777215,1478103162,0,ff93c937,2625797295">sounds（划掉）</d><d p="110.37100,1,25,16777215,1478106110,0,a0326a0b,2625885423">放屁to you笑到醒</d><d p="56.34600,1,25,16777215,1478182244,0,f6747ce8,2629021141">痒</d><d p="102.02200,1,25,16777215,1478182244,0,f6747ce8,2629023691">痒死了</d><d p="4.83700,1,25,16777215,1478308152,0,84852b71,2632567269">郭钰魔塔的人</d><d p="277.01200,1,25,16777215,1478325734,0,466011ce,2633440121">神tm放屁额</d><d p="104.69200,1,25,16777215,1478362358,0,92e76466,2635914519">下巴麻麻的</d><d p="843.05400,1,25,16777215,1478408482,0,4ffad807,2637265949">没人啦，都睡着啦？</d><d p="367.41600,1,25,16777215,1478535138,0,b85a0d8d,2642180777">我</d><d p="103.93800,1,25,16777215,1478614226,0,3b1a52fb,2644240219">哈哈</d><d p="284.53600,1,25,16777215,1478614229,0,3b1a52fb,2644250881">有人吗</d><d p="158.63800,1,25,16777215,1478617860,0,cce189ae,2644353065">德叔好牛逼</d><d p="123.27800,1,25,16777215,1478617910,0,a0af8361,2644502919">天哪好棒</d><d p="100.45100,1,25,16777215,1478621527,0,5725cf22,2644543031">放屁笑尿</d><d p="232.54700,1,25,16777215,1478704280,0,47684150,2646745857">靠技术吃饭，好有快感</d><d p="120.54300,1,25,16777215,1478707970,0,af088024,2646947953">头发的那个笑醒</d><d p="237.02700,1,25,16777215,1478877079,0,a5f82894,2652661043">德玛西亚别跑！</d><d p="79.18600,5,25,16777215,1478883697,0,76151a34,2652988127">就这里.爽</d><d p="89.93900,5,25,16777215,1478883698,0,76151a34,2652989629">就这个feel 倍儿爽</d><d p="182.06000,5,25,16777215,1478883700,0,76151a34,2652992027">就这个feel 倍儿爽</d><d p="185.47300,5,25,16777215,1478883700,0,76151a34,2652992401">就这个feel 倍儿爽</d><d p="346.78800,1,25,16777215,1478963480,0,9c90a002,2656183881">H哈哈</d><d p="27.44700,1,25,16777215,1479006716,0,a322ae2e,2657450893">201621111</d><d p="240.79000,1,25,16777215,1479010320,0,a322ae2e,2657463851">抹胸的别跑</d><d p="18.38400,1,25,16777215,1479056517,0,65f739eb,2660306879">德叔万岁</d><d p="60.73900,1,25,16777215,1479136296,0,82bbb12c,2662717527">罗夏吧，有很小一丝丝想象</d><d p="724.41500,1,25,16777215,1479222702,0,db29cf66,2665008341">这样全程？</d><d p="145.61000,1,25,16777215,1479229275,0,457cd879,2665188679">德叔哪里人？山东德州？</d><d p="169.59700,1,25,16777215,1479254923,0,18ca47d5,2665408989">仿佛真能感受到呼吸的温热</d><d p="508.79700,1,25,9599289,1479272482,0,9e57f806,2665812869">弹幕呢</d><d p="570.99300,1,25,9599289,1479272484,0,9e57f806,2665815731">睫毛好长</d><d p="135.13700,1,25,16777215,1479301772,0,f20ae6bd,2666897581">字幕君可不可以说中文...你打出来英文我也看不懂...</d><d p="171.98700,1,25,16777215,1479301772,0,f20ae6bd,2666900427">德叔是唯一一个我看的男性asmr</d><d p="291.73300,1,25,16777215,1479301775,0,f20ae6bd,2666910651">我想知道这弹幕是实时的吗，现在是晚上9:35，现在在看的打个6</d><d p="104.29200,1,25,16777215,1479521440,0,a16f93eb,2673375525">毫无违和</d><d p="156.52000,1,25,16777215,1479521441,0,a16f93eb,2673377705">山东德州的厉害！</d><d p="366.28400,1,25,16777215,1479574871,0,70c49063,2676644141">现在的扣？</d><d p="395.04400,1,25,16777215,1479574872,0,70c49063,2676645795">还有人没？</d><d p="96.46900,1,25,16777215,1479733756,0,2c4e9740,2682500535">倍儿爽</d><d p="151.95100,5,25,11890,1479741090,0,cce189ae,2682998811">承包德叔</d><d p="174.12600,1,25,16777215,1479747662,0,51726fed,2683226181">呼吸声舒麻</d><d p="324.77500,1,25,16777215,1479776951,0,c77d3f0a,2683515651">有</d><d p="114.18100,1,25,16777215,1479794579,0,fee88db2,2684415287">哈哈哈</d><d p="10.90400,1,25,16777215,1480086663,0,59f5fb7a,2693538163">v</d><d p="19.62400,1,25,16777215,1480086663,0,59f5fb7a,2693539889">h</d><d p="274.93500,1,25,16777215,1480173085,0,69b1ceea,2697166441">容易硬</d><d p="4.54800,1,25,16777215,1480197992,0,8eedbc52,2697786005">第一ヽ(=^･ω･^=)丿</d><d p="66.50100,5,25,16777215,1480259482,0,a61ddf5d,2700739009">纳尼纳尼？</d><d p="37.98000,1,25,0,1480280704,0,f19a16b6,2701177109">boom~</d><d p="294.61100,1,25,0,1480363485,0,ab8d4308,2703586333">头一回感觉痒痒的</d><d p="81.40000,1,25,0,1480428644,0,5e0ea430,2705434143">耳朵怀孕了~ (｡ˇε ˇ｡）</d><d p="135.25600,1,25,0,1480515048,0,e919805e,2707863123">这让我深切怀疑德叔有口音</d><d p="310.86300,1,25,16777215,1480522323,0,d72910b8,2708097189">有</d><d p="87.00500,1,25,16777215,1480525266,0,49e2ed22,2708216419">整个大脑到后背都麻了</d><d p="113.06900,1,25,0,1480597797,0,a33e42be,2710104671">莫名的爽</d><d p="31.23900,1,25,0,1480605098,0,bbc72e47,2710448613">哇塞！！！超棒！！！</d><d p="264.09100,1,25,16777215,1480701751,0,41452f84,2713512109">见叔困</d><d p="298.81800,1,25,16777215,1480701752,0,41452f84,2713512635">6</d><d p="356.67000,1,25,0,1480784471,0,623a4fd4,2717071685">快把自己催眠了</d><d p="199.38900,1,25,16777215,1480856981,0,637e2db9,2720168003">德克萨斯.周</d><d p="9.68800,1,25,16777215,1480874554,0,95ae1acc,2720957461">这不是一张白纸</d><d p="16.50100,1,25,16777215,1480914075,0,f31ff640,2721543403">见叔困=_=</d><d p="65.01500,1,25,16777215,1480939739,0,5102b8cf,2722665531">字幕。太厉害了</d><d p="98.35900,1,25,16777215,1480943340,0,5102b8cf,2722669075">卧槽。。看弹幕笑得睡意全无</d><d p="255.08200,1,25,0,1480954356,0,6d334395,2723394039">拽字幕呢</d><d p="115.81000,1,25,16777215,1481011443,0,7e17c932,2724583529">笑出声</d><d p="98.59200,1,25,16777215,1481119817,0,4354c95a,2728100953">后腰好痒啊啊啊啊啊</d><d p="125.48800,1,25,16777215,1481119818,0,4354c95a,2728102609">we want啵啵啵啵啵啵</d><d p="203.56700,1,25,0,1481123490,0,7321132d,2728355525">别动我耳朵！</d><d p="288.45500,1,25,16777215,1481123493,0,fb0ae933,2728361203">前面硬的别走</d><d p="312.34600,1,25,16777215,1481123493,0,fb0ae933,2728362489">有</d><d p="110.51700,1,25,16777215,1481127167,0,c4a67a64,2728536111">哈哈哈哈哈放屁</d><d p="3.34700,1,25,16777215,1481127167,0,26a4df9a,2728536485">来看这张纸......</d><d p="6.94100,4,25,16777215,1481127167,0,26a4df9a,2728536907">来看这张纸...</d><d p="22.31400,4,25,16777215,1481127168,0,26a4df9a,2728538205">用手竟然不能在上面写字....</d><d p="47.41600,4,25,16777215,1481127169,0,26a4df9a,2728540119">声音是从我的嘴里发出的....</d><d p="94.95100,4,25,16777215,1481127171,0,26a4df9a,2728542401">这个屁是我为你放的.....</d><d p="18.38900,1,25,16777215,1481180628,0,d1b48bde,2729742999">这是一张被我施加魔法的白纸</d><d p="50.06200,1,25,16777215,1481180630,0,d1b48bde,2729744331">长得好像肉丝里的野人</d><d p="208.23600,4,25,16707842,1481209865,0,5d611ca4,2731040425">世界之谜--德叔的设备</d><d p="305.76800,1,25,16777215,1481263327,0,c3f39151,2732161195">我一个男的为什么要看这个</d><d p="620.94500,1,25,16777215,1481267025,0,963b5426,2732354439">n</d><d p="989.19800,1,25,16777215,1481292627,0,4354c95a,2733683787">有点像山芋老公xx</d><d p="107.07900,1,25,16777215,1481292651,0,9bee1012,2733776857">字幕英语功底不错</d><d p="379.42300,1,25,16777215,1481335844,0,8a9e1ad,2734786135">nnn</d><d p="685.02400,1,25,16777215,1481335845,0,8a9e1ad,2734786659">nnnnn</d><d p="53.64500,1,25,16777215,1481346070,0,9ed4fb63,2735214445">感觉头发变少了</d><d p="184.22200,5,25,16777215,1481389286,0,e2bf88c0,2737945569">德叔真的好厉害</d><d p="0.09200,1,25,41194,1481472720,0,6491f57e,2741508011">第一</d><d p="15.04600,1,25,41194,1481472722,0,6491f57e,2741512689">Almost？</d><d p="21.91900,1,25,41194,1481472722,0,6491f57e,2741514135">看了半天也不知道啥意思 almost啥意思求翻译</d><d p="5.20000,1,25,41194,1481472723,0,6491f57e,2741516089">qlmotzmmm</d><d p="9.00800,1,25,41194,1481472723,0,6491f57e,2741516771">almost是几乎</d><d p="114.79900,1,25,41194,1481472725,0,6491f57e,2741522879">哈哈哈哈哈哈哈哈放屁to you 要知道现在已经十二点了</d><d p="140.62000,1,25,41194,1481472726,0,6491f57e,2741524517">德叔澳洲口音阿</d><d p="169.87700,1,25,41194,1481472727,0,6491f57e,2741526139">时间太短睡不着</d><d p="241.19100,1,25,16777215,1481475690,0,7b1b8a72,2741689055">腰好痒。。。你们会吗</d><d p="218.46200,1,25,16777215,1481479338,0,f6929869,2741746033">德玛西亚笑出声</d><d p="733.77200,1,25,16777215,1481508651,0,d54d81d4,2742061523">轻松承包</d><d p="533.54400,1,25,16777215,1481608976,0,4cf2e943,2745163079">弹幕在这里</d><d p="61.48400,1,25,0,1481634586,0,27e1bcf9,2746296709">长得像我爸…………</d><d p="43.83900,5,25,15138834,1481638252,0,6491f57e,2746545427">底下空耳你够↓</d><d p="255.37300,1,25,41194,1481638253,0,8526ab06,2746549041">大家睡前还要交流一下哪里痒的问题吗……………</d><d p="102.43400,1,25,16777215,1481641876,0,2522c660,2746634167">哈哈哈哈哈哈哈哈哈</d><d p="73.68700,1,25,6830715,1481666773,0,660412ff,2747107287">赞赞赞赞赞赞</d><d p="93.31100,1,25,16777215,1481699039,0,bb8ed030,2747918737">能想象到是一个男的光着脚丫子对着一个摄像头晃悠晃悠？</d><d p="207.01500,1,25,16777215,1481734869,0,f8910219,2749482781">德先生和赛先生</d><d p="115.51300,1,25,16777215,1481803693,0,d7a60ae2,2751054491">伊涅斯塔啊</d><d p="135.26600,1,25,16777215,1481814699,0,d910e056,2751755493">放屁那个哈哈哈哈哈哈哈 笑得我睡不着</d><d p="107.35000,1,25,0,1481879102,0,593ee184,2753141437">每次休息都听嘿嘿嘿</d><d p="180.91500,1,25,0,1481879103,0,593ee184,2753144711">呼吸声。腰好痒。挠挠</d><d p="47.01800,4,25,8700107,1481958235,0,e8c816bd,2756350081">from my month</d><d p="121.66300,1,25,16777215,1481987461,0,f01e0abc,2758055443">说伊列斯塔的，你站住</d><d p="207.55400,1,25,0,1481994069,0,b9e82142,2758512655">德玛西亚的你别跑</d><d p="1.34700,1,25,6830715,1481997775,0,7885d13e,2758692687">基佬紫</d><d p="87.71400,1,25,16777215,1482005057,0,545596db,2758760879">wox好爽</d><d p="44.01600,1,25,16777215,1482048264,0,30d26cc2,2760389205">塞要死是啥</d><d p="115.55000,1,25,16777215,1482048267,0,30d26cc2,2760396109">。。。。放屁</d><d p="284.06400,1,25,16777215,1482048269,0,30d26cc2,2760405525">那个基佬。。</d><d p="14.64300,1,25,16777215,1482048288,0,30d26cc2,2760467259">基佬们举手</d><d p="876.77400,1,25,16777215,1482149295,0,9674df81,2763918833">求野生字幕菌</d><d p="335.63500,1,25,0,1482217432,0,77adc474,2765908729">男生看请扣1</d><d p="105.42100,1,25,16777215,1482476608,0,6f0476cb,2773971201">放屁的笑醒</d><d p="111.92000,1,25,16777215,1482552751,0,c4b7ef2,2776695939">哈哈哈，很可爱www</d><d p="18.35000,1,25,0,1482656723,0,24c21718,2781516559">不行   看见他就困了。</d><d p="88.93000,1,25,0,1482757790,0,cba1f1b6,2784972463">和76一样发际线高</d><d p="466.04700,1,25,0,1482771701,0,43a8fa23,2785627421">这尼玛叫专业</d><d p="30.02300,1,25,16777215,1482851485,0,556ce108,2788133591">almost不是几乎的意思吗？</d><d p="224.05800,1,25,16777215,1482937889,0,a24a17b8,2790690443">强忍着不弯</d><d p="432.46500,1,25,16777215,1482937918,0,db7af885,2790774349">完全没反应啊</d><d p="307.66500,1,25,0,1482941526,0,ddb9ab5f,2790795089">感觉好像小时候我爷爷哄我睡觉……</d><d p="96.96600,1,25,16777215,1482991376,0,11cd0c42,2791789877">德叔知不知道中国有这么多粉丝</d><d p="52.23300,1,25,16777215,1483027977,0,55be8501,2793422210">第十三周目回顾</d><d p="21.09100,1,25,16777215,1483030912,0,f1156266,2793504877">热 好好听</d><d p="1.95000,4,25,16777215,1483034520,0,ce592203,2793514027">alomst inaudible sounds</d><d p="122.19700,1,25,0,1483117305,0,2463f658,2796633917">听不懂啊</d><d p="59.95600,1,25,16777215,1483193445,0,8ca6e4e7,2799790001">罗夏 tonggan</d><d p="59.95600,1,25,16777215,1483193445,0,8ca6e4e7,2799791159">罗夏 同感</d><d p="622.57000,1,25,16777215,1483214655,0,44eebedf,2800731973">单眼3d手势引导啊</d><d p="406.09500,1,25,16777215,1483268874,0,7aff88f3,2803414657">都睡着了</d><d p="67.43800,1,25,0,1483358923,0,55ceb576,2807790195">好听</d><d p="475.20100,1,25,0,1483456284,0,c550c9ab,2811286863">飞哦</d><d p="506.54100,1,25,0,1483456284,0,c550c9ab,2811288717">飞哦</d><d p="49.55500,1,25,16777215,1483456308,0,ce531423,2811369773">么么打</d><d p="30.20900,1,25,16777215,1483556616,0,4f102284,2814670577">2017</d><d p="567.48800,1,25,0,1483632766,0,c024ea2c,2817375897">男asmr就听德叔</d><d p="435.27700,1,25,16777215,1483635683,0,6907f04c,2817450171">非常专业！</d><d p="116.58200,1,25,16777215,1483635688,0,87794997,2817458719">这弹幕有毒</d><d p="82.38600,1,25,0,1483678876,0,917950e9,2818242335">我腿软了。。。</d><d p="10.09000,1,25,0,1483697167,0,c5463312,2818972731">我是德派教主，老德</d><d p="471.83800,1,25,16777215,1483708142,0,6b8e9584,2819670409">那是你没戴上好耳机认真听</d><d p="107.05400,1,25,0,1483708173,0,4354c95a,2819804263">放屁 to you</d><d p="111.13000,1,25,0,1483941747,0,8952a866,2829711529">英语听力现在开始</d><d p="139.13300,1,25,16777215,1483974683,0,458e2b02,2831337079">德叔在看弹幕</d><d p="174.72700,5,25,16777215,1483974701,0,947e29bd,2831403179">德叔刚刚说来神经病!？</d><d p="40.54000,4,18,16777215,1483974707,0,67364add,2831418975">from my mouse</d><d p="312.90900,4,25,16777215,1483974713,0,67364add,2831438231">哈哈</d><d p="320.74000,4,25,16777215,1483974713,0,67364add,2831439677">哈哈</d><d p="324.91900,1,25,16777215,1484057437,0,e97c2d9d,2834004767">2019年考古！</d><d p="972.84000,1,25,16777215,1484057449,0,e97c2d9d,2834054673">弹幕呢？</d><d p="168.50500,1,25,0,1484061114,0,1667baf4,2834284379">我现在满脑子都是放屁to you要笑死了</d><d p="168.50500,1,25,0,1484061115,0,1667baf4,2834286869">我现在满脑子都是放屁toyuo要笑死了</d><d p="168.50500,1,25,0,1484061115,0,1667baf4,2834288029">我现在满脑子都是放屁tuyou要笑死了</d><d p="271.13800,1,25,16777215,1484064755,0,dede2634,2834392419">哪里都痒 后腰格外</d><d p="121.06700,1,25,16777215,1484067664,0,531c6048,2834454311">我上小学的表弟和他好像，出戏</d><d p="96.74900,5,25,16707842,1484067682,0,885a9f9e,2834488335">放屁to you的我不打死你</d><d p="87.74300,1,25,16777215,1484143805,0,9e6ad354,2836941231">够专业  这才叫asmr</d><d p="292.43400,1,25,0,1484143856,0,8ba1e427,2837153011">双手打字</d><d p="347.15200,1,25,0,1484143857,0,8ba1e427,2837156597">微微一湿，以表敬意</d><d p="407.90300,1,25,16777215,1484143857,0,959d55e5,2837157107">脸都红了</d><d p="51.67900,1,25,0,1484147508,0,a3a42061,2837339727">聪明的人才能看见写了什么</d><d p="81.63600,1,25,0,1484151154,0,b7238169,2837470797">舔耳2333333</d><d p="648.11600,1,25,0,1484154097,0,832e9b17,2837597151">用vr食用效果更佳</d><d p="107.81600,1,25,0,1484161439,0,d4132ce8,2837727313">弹幕哈哈哈</d><d p="41.24200,1,25,16777215,1484165084,0,f2f8adac,2837747521">?</d><d p="58.78300,1,25,16777215,1484165085,0,f2f8adac,2837747827">am   lost是迷失自我的意思</d><d p="63.61100,1,25,16777215,1484233874,0,87b23b48,2840338313">。</d><d p="226.34200,1,25,10092339,1484237553,0,d068d13a,2840597353">有人嘛。</d><d p="300.20000,1,25,10092339,1484237554,0,d068d13a,2840600469">硬的都是什么心态...</d><d p="113.22100,1,25,16777215,1484262454,0,1ad3deec,2840984579">干脆床头放德叔雕像 不会失眠</d><d p="229.21000,1,25,16777215,1484262456,0,1ad3deec,2840986273">酥酥麻麻的好爽</d><d p="503.66300,1,25,16777215,1484262460,0,1ad3deec,2840988735">德叔是真专业 不是那些主播</d><d p="561.27200,1,25,16777215,1484262461,0,1ad3deec,2840989277">我想找德叔按摩</d><d p="627.00300,1,25,16777215,1484262462,0,1ad3deec,2840989911">这tm是叫你听的</d><d p="45.70100,1,25,0,1484334193,0,d1a5d097,2844410327">讲真  德叔张口我就困</d><d p="120.09300,1,25,16777215,1484399380,0,c067578d,2847620665">只有得得得的声音</d><d p="603.87100,1,25,16777215,1484413279,0,3a1ac0dc,2848576257">幸存者1号</d><d p="51.24400,1,25,16777215,1484413280,0,da965678,2848579423">舔耳</d><d p="217.40900,1,25,16777215,1484413315,0,6c105aef,2848656037">唉呀老是吹气耳朵难受</d><d p="108.30300,1,25,16777215,1484485792,0,5eddd89b,2851982255">妈哒这觉不睡了弹幕笑醒了</d><d p="202.04600,1,25,0,1484489412,0,164e8d0a,2852082869">tribber</d><d p="222.04200,1,25,0,1484489413,0,164e8d0a,2852084497">前面的是tridder</d><d p="92.53900,1,25,16777215,1484536260,0,89c7fc9a,2853452749">剃头罗夏</d><d p="275.13100,1,25,16777215,1484575845,0,b8048afd,2856619083">我怀疑耳机其实是会吹气的·-·</d><d p="341.34700,1,25,16707842,1484579481,0,d09679c6,2856808341">1</d><d p="32.29100,1,25,16777215,1484597043,0,1e997064,2857443993">油管下视频免费的</d><d p="552.28100,1,25,0,1484626375,0,f7ab3847,2858280437">王炸</d><d p="83.55600,1,25,16777215,1484632974,0,eaf57677,2858754117">&gt;O&lt;</d><d p="399.11300,1,25,0,1484658579,0,3519e3e9,2860503803">。。</d><d p="109.06200,1,25,16777215,1484669538,0,4e1d9b9c,2861281807">哈哈哈哈哈哈哈</d><d p="317.64800,1,25,16777215,1484672465,0,b3908143,2861426425">2017 1 28</d><d p="69.61400,4,25,16707842,1484748638,0,668dc199,2865408283">ass light</d><d p="71.66700,4,25,16707842,1484748638,0,668dc199,2865409767">talk</d><d p="77.10700,4,25,16707842,1484748639,0,668dc199,2865414169">夹死屌</d><d p="83.56300,4,25,16707842,1484748639,0,668dc199,2865415453">edge</d><d p="74.27900,4,25,16707842,1484748641,0,668dc199,2865424265">屁股灯和屁谈话...</d><d p="99.52900,4,25,16707842,1484748642,0,668dc199,2865430381">睡意全无</d><d p="96.15300,1,25,16777215,1484752290,0,435afe6,2865689251">放屁其实是from me啦，哈哈</d><d p="246.09900,1,25,16777215,1484752304,0,a19b40a3,2865758505">湿了</d><d p="331.33400,1,25,0,1484755941,0,adc1b6b9,2865929855">哈哈哈哈哈</d><d p="323.59300,1,25,16777215,1484755961,0,d6300818,2866002047">前面的。现在才2017  1 18</d><d p="100.28100,5,25,16777215,1484827708,0,4abdca7f,2869344040">放屁的我想打死你</d><d p="58.67100,1,25,0,1484831381,0,420bd834,2869758066">安静</d><d p="94.83700,1,25,16777215,1484835007,0,7b9f3054,2869913260">我曹我头皮发麻了</d><d p="348.21200,1,25,16777215,1484835011,0,7b9f3054,2869941530">0</d><d p="60.65000,1,25,16777215,1484838715,0,63103851,2870539406">嗯嗯嗯，不错我睡着了</d><d p="158.01500,4,25,16711680,1484917777,0,f3b0bb2d,2874915224">meet you</d><d p="118.72200,5,25,6830715,1484921430,0,21cb71d0,2875231154">午时已到</d><d p="158.21100,1,25,16777215,1484921431,0,239db5f8,2875233754">德州的别走</d><d p="225.33800,1,25,16777215,1484921432,0,239db5f8,2875240844">一个男的看德叔竟然如此的着迷</d><d p="198.13300,1,25,16777215,1484925104,0,f8ef25b3,2875671150">设备太好了</d><d p="643.88200,1,25,16707842,1484931710,0,d09679c6,2876130642">都睡着了？</d><d p="2.99100,1,25,16777215,1485007830,0,8316602e,2880095180">.</d><d p="97.91800,5,25,15138834,1485021772,0,e68c2831,2881062322">放屁</d><d p="96.19900,5,25,15138834,1485021773,0,e68c2831,2881063202">放屁</d><d p="108.78900,1,25,16777215,1485036363,0,eea63d7d,2881210712">另一个小伙伴好啊</d><d p="168.67100,1,25,0,1485097876,0,b86c02f0,2885157608">我是德州的</d><d p="82.02800,1,25,16777215,1485101533,0,58f92ee,2885439114">还是德叔的视频最有感觉</d><d p="345.04200,1,25,16777215,1485101538,0,58f92ee,2885460072">1</d><d p="210.02800,1,25,16777215,1485101556,0,27421155,2885533356">妹子举手</d><d p="297.52000,1,25,16777215,1485101558,0,27421155,2885539138">双手打字</d><d p="29.74100,4,25,16777215,1485101569,0,87b38364,2885580282">这是张假纸</d><d p="55.27500,4,25,16777215,1485101570,0,87b38364,2885582402">我用嘴学出来的声音</d><d p="134.13100,1,25,16777215,1485104490,0,1afda274,2885699570">伊涅斯塔</d><d p="401.97800,1,25,16777215,1485162340,0,2d559276,2888269298">人？！</d><d p="174.14900,1,25,16777215,1485173323,0,56762c4c,2889178372">哈哈</d><d p="357.12700,1,25,0,1485346133,0,3037127d,2899351268">2017   1  25</d><d p="91.78600,1,25,15138834,1485349740,0,d3810c69,2899390474">主播一声吼，梦里抖三抖。</d><d p="97.01100,5,25,15138834,1485349741,0,d3810c69,2899393574">主播一声吼，梦里抖三抖。</d><d p="10.26300,4,25,41194,1485406911,0,b2d96ae6,2902356586">见叔困</d><d p="14.35000,5,25,9487136,1485406912,0,b2d96ae6,2902358206">见叔困</d><d p="54.93500,1,25,16777215,1485447139,0,391f1b38,2905719292">所以纸的沙沙声是他嘴里发出来的？</d><d p="366.55500,1,25,16777215,1485450084,0,e3d41a9b,2905953954">今天是除夕了</d><d p="10.71400,1,25,0,1485533541,0,2e251ec8,2911906842">见叔困</d><d p="36.04300,1,25,0,1485547449,0,b70052d,2912594628">笨的人看不见纸上字</d><d p="129.52600,1,25,16777215,1485616312,0,79c5d4c3,2917489200">刮胡子变成擦纸了…</d><d p="167.69700,1,25,16777215,1485616313,0,79c5d4c3,2917492836">这个是不是去完底噪的声音呐？</d><d p="817.55700,1,25,16777215,1485619976,0,c41ec6ee,2917787132">GG</d><d p="268.94200,1,25,16777215,1485622864,0,d386c917,2917816732">gta4的别走</d><d p="277.92000,1,25,0,1485695391,0,94272dc0,2921585932">见叔困</d><d p="55.72000,1,25,0,1485709292,0,aeaf874a,2922642178">关上听感觉德叔在舔耳..？？？</d><d p="15.05500,1,25,6830715,1485709294,0,b0ea920b,2922647528">基佬紫</d><d p="18.30600,1,25,6830715,1485709294,0,b0ea920b,2922647914">基佬紫</d><d p="268.63100,1,25,16777215,1485712975,0,e6fc1336,2922812032">触发不了……</d><d p="847.02700,1,25,16777215,1485716588,0,ac8b4d5d,2922830874">好大一个痘痘好大一个痘痘</d><d p="343.65500,1,25,16777215,1485789069,0,e0e75339,2926833186">1</d><d p="101.49400,1,25,16777215,1485864498,0,c509c873,2930766914">just a little 屁</d><d p="290.50200,1,25,16777215,1485864539,0,4af3b070,2931002450">才发现德叔有点像我们的体育老师</d><d p="219.04300,1,25,16777215,1485868151,0,aaa4103f,2931073834">21:11</d><d p="986.31800,1,25,0,1485871854,0,b8bbce9f,2931727936">都睡了</d><d p="349.86100,1,25,0,1485879120,0,862e8815,2932108698">1</d><d p="130.03100,1,25,16777215,1485879163,0,f28c20b3,2932294178">感觉嘴里有口臭</d><d p="230.43400,1,25,15138834,1485879165,0,f28c20b3,2932302566">鼻子通气了</d><d p="468.43000,1,25,16777215,1485882061,0,66fb62e3,2932361626">太专业了 我现在都快坚持不住了</d><d p="480.13300,1,25,16777215,1485882061,0,66fb62e3,2932363156">得戴上耳机认真听才行</d><d p="318.67000,1,25,16777215,1485882075,0,27052891,2932414214">有些人直男癌</d><d p="34.71200,1,25,16777215,1485885767,0,ba2c5586,2932651510">德叔你是个假人</d><d p="357.21500,1,25,16777215,1485958241,0,321ee97b,2936923758">1</d><d p="208.60700,1,25,16777215,1485961863,0,429e4510,2937071792">德玛西亚的你出来哈哈哈哈哈哈</d><d p="251.33200,1,25,16777215,1485961865,0,429e4510,2937081142">同腰好痒 感觉每吹一口气都要虎躯一震</d><d p="299.72200,1,25,16777215,1485961866,0,429e4510,2937088374">痒的笑出了声</d><d p="84.95800,1,18,16777215,1485961870,0,88fb3744,2937111370">看的多会不会变性啊</d><d p="493.59000,1,18,16777215,1485961877,0,88fb3744,2937155540">看了半天我才发现后面的画也是关键</d><d p="978.41000,1,18,16777215,1485961882,0,88fb3744,2937189374">没了</d><d p="89.54500,1,25,16777215,1485965526,0,797fc64c,2937465144">神TM76！233333</d><d p="31.76400,1,25,14811775,1485965549,0,727de517,2937591092">First：德叔是真的专业</d><d p="329.81000,1,25,0,1485968477,0,63c94012,2937795014">哈哈</d><d p="344.32100,1,25,0,1485968477,0,63c94012,2937795842">1</d><d p="404.89600,1,25,0,1485968478,0,63c94012,2937799504">嗯</d><d p="451.57500,1,25,0,1485968480,0,63c94012,2937804402">在托我下巴壳？</d><d p="110.49000,1,25,0,1485968495,0,127fd7de,2937855990">徳叔设备棒德叔活好</d><d p="48.56000,1,25,0,1485968506,0,55e53e1f,2937890544">mua</d><d p="257.14200,1,25,0,1485972174,0,1909b38d,2938050032">练听力来了</d><d p="402.01000,1,25,16777215,1485983131,0,b29191c0,2938196674">唯一能接受男性做的asmr</d><d p="110.03400,1,25,0,1486018994,0,b52bc21,2939837054">这时候的德叔很瘦又帅后来德叔都有白头发了，心疼</d><d p="187.43000,1,25,16777215,1486029983,0,8c262cfb,2940800722">德叔都不用戴耳机的。。</d><d p="341.88700,1,25,16777215,1486037310,0,1a04dc98,2941518342">1</d><d p="664.51100,1,25,16777215,1486048302,0,9ecbd510,2942758878">我咋觉得有点像罗本…</d><d p="266.87900,1,25,16777215,1486062195,0,c4b7ef2,2943485506">抹窗？</d><d p="453.23700,1,25,0,1486084160,0,b6958b5f,2943793664">德叔好像普京……</d><d p="344.12100,1,25,16777215,1486087815,0,862a143b,2943951640">2017年2月30</d><d p="432.23700,1,25,16777215,1486101745,0,b27c1d4d,2945141178">好爽</d><d p="94.84900,1,25,0,1486131009,0,910947d8,2947796174">黄字空调</d><d p="503.57900,1,25,16777215,1486138336,0,664525d0,2948583828">看他的手动感觉背后一阵酥麻</d><d p="33.43600,1,25,16777215,1486152240,0,6491f57e,2949199298">2017-2-4 凌晨4点整</d><d p="44.76700,4,25,15138834,1486152241,0,6491f57e,2949199846">是mouth好吗mouse是老鼠</d><d p="117.37600,4,25,15138834,1486152243,0,6491f57e,2949201862">what you want</d><d p="1037.93900,4,25,41194,1486152244,0,6491f57e,2949203324">都睡着了？ 2017-2-4 凌晨四点多</d><d p="41.31500,1,25,0,1486227719,0,83ac154e,2955614762">厉害了，我的叔</d><d p="81.49000,1,25,0,1486231376,0,b61ae59a,2955753812">我整个人都在发麻我去</d><d p="93.45900,1,25,0,1486235007,0,a1f3f2e2,2955803152">德叔说话真的催眠</d><d p="141.02400,1,25,16777215,1486274525,0,657bbe8d,2957313494">字幕君听力厉害了</d><d p="111.12400,1,25,0,1486303836,0,8a446e8c,2960165360">说实话不能看长相 德叔很专业</d><d p="163.14500,1,25,0,1486314108,0,aebf9658,2961124726">罗本</d><d p="13.95200,1,25,16777215,1486317754,0,a507ab3c,2961242982">德叔良心</d><d p="169.92600,1,25,16777215,1486317768,0,24c21718,2961270154">受不了的出门右转谢谢，没有人强迫你们看。</d><d p="113.78200,1,25,0,1486325098,0,b154f59,2961419000">设想一下，如果十年后的英语四级听力是这样的</d><d p="78.28000,1,25,16777215,1486393915,0,f413c42e,2966072324">很皮</d><d p="83.86000,1,25,16777215,1486393915,0,f413c42e,2966073948">睡觉？不存在的</d><d p="321.00100,1,25,16777215,1486393919,0,f413c42e,2966095888">有人？不存在的</d><d p="290.04500,1,25,16777215,1486404134,0,ca01b890,2966614380">睡觉了晚安</d><d p="87.07000,1,25,16777215,1486465656,0,500024b9,2969786516">脑补德叔舔耳PLAY</d><d p="3.31700,1,25,16777215,1486486918,0,b39e82f6,2971767186">德叔:来，按我这个画可得SSR</d><d p="220.75400,1,25,0,1486653081,0,ea86ae78,2981809780">敢问在座都是男的女的？？？</d><d p="390.55100,1,25,0,1486653084,0,ea86ae78,2981827502">现在是北京时间2017年2月9号</d><d p="92.59900,1,25,16777215,1486653113,0,72fdddf8,2981998308">底下听力满分</d><d p="30.70300,1,25,0,1486659676,0,caeccac5,2982356926">见叔困</d><d p="106.73000,1,25,0,1486659678,0,caeccac5,2982364230">哈哈</d><d p="156.05500,1,25,0,1486659679,0,caeccac5,2982366848">放屁那个站住</d><d p="255.01000,1,25,0,1486659680,0,caeccac5,2982372656">神他妈德玛西亚</d><d p="324.81400,1,25,0,1486659682,0,caeccac5,2982376274">叔的手好美</d><d p="340.22800,1,25,0,1486659682,0,caeccac5,2982377084">手给我摸摸</d><d p="363.83400,1,25,0,1486710184,0,8a43a26e,2984497412">哈的我耳朵热...</d><d p="223.28300,1,25,16777215,1486735815,0,b2d7de45,2986824492">哈哈哈前面那个在胸口摸的站住</d><d p="342.05500,1,25,16777215,1486789313,0,a71b434d,2989591220">1</d><d p="19.51900,1,25,0,1486792964,0,895557d9,2989844872">啊哈</d><d p="194.95200,1,25,16777215,1486818559,0,34f71c65,2991784954">还是喜欢老番茄的</d><d p="231.65600,1,25,0,1486818566,0,140cd9d5,2991826766">女哒</d><d p="80.83700,1,25,0,1486825898,0,43b33f3,2992613130">很舒服</d><d p="123.76700,1,25,0,1486825898,0,43b33f3,2992617018">脑补舔耳的带我一个</d><d p="271.75200,1,25,0,1486886687,0,895557d9,2995453322">听流口水了</d><d p="14.95900,1,25,16777215,1486918861,0,bb5f3235,2997652286">没人？</d><d p="59.94400,5,25,6830715,1487002368,0,30cd5b75,3001359420">我想说在座的各位都是女生吗</d><d p="269.88700,1,25,16777215,1487002378,0,1945d3d0,3001388492">苏</d><d p="404.95600,1,25,0,1487019911,0,6eb3e4e,3001691642">2017.</d><d p="131.97800,1,25,0,1487095340,0,e7d5e5a5,3005093578">见德困</d><d p="321.71100,1,25,16777215,1487239605,0,5468dd5a,3010677888">头皮发麻</d><d p="32.28400,1,25,16777215,1487264478,0,84bf199b,3012288512">... 為什麼即使是呼吸聲我也發麻了…</d><d p="123.15500,1,25,16777215,1487264481,0,84bf199b,3012298428">我的腰orz</d><d p="387.31000,1,25,16777215,1487268127,0,43f0087d,3012390562">抓你胸帮助睡眠啊（一本正经）</d><d p="78.96900,1,25,15138834,1487434325,0,bd914dd7,3020727138">hhhhh</d><d p="219.54600,1,25,16777215,1487495122,0,2c0fd32f,3023590908">话说听这个视频的人难道平时都喜欢听人家砸吧嘴吗？</d><d p="325.87500,1,25,16777215,1487495124,0,2c0fd32f,3023598936">万一他有口臭怎么办。。</d><d p="118.15900,1,25,0,1487517065,0,649da989,3025105910">身为一个男的看德叔我是不是废了</d><d p="247.06200,1,25,16777215,1487534657,0,dc43b853,3025744092">德叔英文名:德鲁伊</d><d p="39.84100,1,25,16777215,1487603518,0,f5e0989c,3028624470">20170220</d><d p="82.73000,1,25,16707842,1487682596,0,d09679c6,3031342718">后面的是拼图吧</d><d p="67.70800,1,25,16777215,1487757985,0,bb78712d,3033896836">有基佬吗？举个手(｡･ω･｡)ﾉ</d><d p="149.81500,1,25,16777215,1487757986,0,bb78712d,3033903558">没有人…了吗⁄(⁄ ⁄ ⁄ω⁄ ⁄ ⁄)⁄（请自行脑补）</d><d p="15.19600,1,25,0,1487779929,0,4ca96331,3035288232">手控死了</d><d p="103.18900,1,25,16777215,1487840757,0,74cc1dd,3037181948">本来困了 弹幕放屁一下笑清醒..</d><d p="264.45800,1,25,16777215,1487859037,0,f6b7890d,3038266914">屁股右面痒怎么办</d><d p="99.10200,1,25,16777215,1487866378,0,3063d5d7,3038771846">尼玛放屁笑的我都睡不着了</d><d p="157.02600,1,25,16777215,1487869267,0,6cf85ac2,3038792488">底噪感人</d><d p="541.49600,1,25,0,1487955703,0,cfdd60d1,3042409458">有电脑端的吗？前面那个麻烦举报下好吗？</d><d p="399.46300,1,25,0,1487981329,0,adefda17,3042774864">微湿的过来  我硬给你看</d><d p="88.05300,1,25,0,1487988653,0,164e8d0a,3043083788">背后的画好漂亮</d><d p="106.13000,1,25,0,1487988655,0,164e8d0a,3043084748">德叔靠什么吃饭</d><d p="81.81300,1,25,0,1488031855,0,811503d8,3046195064">那幅画～</d><d p="76.83200,1,25,16707842,1488035517,0,3e0a8e52,3046506800">男生。。直男</d><d p="338.77700,1,25,16707842,1488039122,0,3e0a8e52,3046527412">1</d><d p="205.02900,1,25,41194,1488042116,0,4b706161,3046892296">德克萨斯·周的别跑笑死我了</d><d p="348.22600,1,25,41194,1488042119,0,4b706161,3046898142">带节奏的起开</d><d p="93.95300,1,25,16777215,1488088978,0,3ef0833,3048648952">羅夏真的像………</d><d p="26.72300,1,25,0,1488110917,0,79d72dd0,3049952278">almost几乎</d><d p="13.92900,1,25,16707842,1488128509,0,c5ef4b73,3051064572">为什么我现在一听asmr就有一种想把耳机摘下来扔掉的感觉（非常强烈）</d><d p="66.87300,1,25,16777215,1488135808,0,75376d3a,3051159804">有点不习惯嘴巴发出的声音。。。？</d><d p="205.35600,1,25,16777215,1488208291,0,1edf928d,3053508234">德叔英文名是Geman uncle</d><d p="293.96400,4,25,15138834,1488381114,0,990b159b,3059002280">菊花狗辈</d><d p="349.87800,1,25,16777215,1488381115,0,990b159b,3059007034">边触发扁运功</d><d p="493.45400,4,18,16777215,1488381118,0,990b159b,3059016406">偷偷承包德叔</d><d p="979.90400,1,25,16777215,1488597113,0,c6083c5b,3065904276">为嘛看asmr还分性别，脑子里在想什么sogou.comO_o</d><d p="105.55400,1,25,0,1488654200,0,48429b84,3069562746">弹幕有毒</d><d p="20.30600,1,25,0,1488723027,0,8e6df40f,3073034442">见叔困</d><d p="341.07600,1,25,16777215,1488766209,0,40cd721f,3074008716">1</d><d p="404.10800,1,25,16777215,1488816770,0,88fb57ae,3076305978">看你们这么。性。奋。睡的着吗？</d><d p="347.37000,1,25,16777215,1488819693,0,31899977,3076373344">1</d><d p="826.08400,1,25,16777215,1488913412,0,9f9ad512,3079195220">YY</d><d p="18.04400,1,25,0,1488985882,0,8e6df40f,3081527374">QQ牛力滋哟!</d><d p="351.77800,1,25,16777215,1489165268,0,13a4d434,3087878174">看他的手就觉得特别困</d><d p="63.38000,1,25,16777215,1489421542,0,c011ff82,3099714804">女生举手</d><d p="210.16100,1,25,16777215,1489421545,0,c011ff82,3099721758">德叔的视频好有感觉啊</d><d p="116.00600,1,25,0,1489677071,0,4354c95a,3108109918">放屁哈哈哈哈哈哈哈哈</d><d p="46.86200,1,25,16777215,1489683713,0,748b3e65,3108524844">哇年轻的德叔qwq</d><d p="13.83800,1,25,16777215,1489756160,0,d0a3dc09,3110805704">这次的底躁简直了</d><d p="127.75600,1,25,16777215,1489773745,0,baa44b3d,3111968206">神弹幕</d><d p="66.41400,1,25,16777215,1489838931,0,aabc47fd,3115115884">没 男的</d><d p="109.23900,1,25,16777215,1489849902,0,48b07328,3116047210">哈哈哈哈哈哈，看弹幕笑醒</d><d p="86.48500,1,25,16777215,1489899696,0,1bf6486e,3117982342">就德叔 感觉最良心 。</d><d p="167.91100,1,25,16777215,1489899697,0,1bf6486e,3117988844">我石更了！</d><d p="203.72000,1,25,16777215,1489899697,0,1bf6486e,3117991596">我就感觉他的设备最好 感觉最棒。</d><d p="61.42900,1,25,16777215,1489903378,0,4bb10081,3118359880">好久没这么期待会在哪里痒了</d><d p="180.40000,1,25,16777215,1489925287,0,b0095141,3119649864">腰痒痒(*/ω＼*)</d><d p="265.33700,1,25,16777215,1489932603,0,aebc6d3e,3120290662">德叔把你的嘴闭上</d><d p="386.57000,1,25,16777215,1489936311,0,cd914c40,3120899332">u</d><d p="229.97000,1,25,16777215,1489939927,0,e83cb836,3120960658">德叔全名德莱厄斯吧</d><d p="254.31900,1,25,0,1490015391,0,c78b0858,3123372232">德鲁伊好出戏</d><d p="112.14300,1,25,0,1490022712,0,664f746f,3123885772">笑出声</d><d p="341.20100,1,25,16777215,1490029293,0,974f48a4,3124118632">很有灵性</d><d p="618.74900,1,25,16777215,1490115669,0,364bfc93,3127012820">幸存者2号</d><d p="648.00600,1,25,16777215,1490115669,0,364bfc93,3127013802">没呢</d><d p="467.66600,1,25,16777215,1490191852,0,1875f4d0,3129521210">头皮酥麻</d><d p="82.63200,1,25,16777215,1490195497,0,f2fb1fe5,3129715014">对德叔背后的画很感兴趣</d><d p="104.48900,1,25,16777215,1490331695,0,2a006b2d,3133833162">放屁的hhhhh</d><d p="283.24300,1,25,0,1490364614,0,3a495dad,3135608260">机械舞</d><d p="96.90100,1,25,0,1490475902,0,4634bfe8,3142007074">哈哈哈哈哈不存在的</d><d p="148.55500,1,25,0,1490475903,0,4634bfe8,3142007470">看弹幕睡不着</d><d p="96.90400,1,25,16777215,1490800268,0,11f4a3ab,3154705802">asmr千千万 还是德叔深得我心</d><d p="45.70000,1,25,16777215,1491044842,0,160bf86e,3163501552">买要死</d><d p="99.19500,1,25,16777215,1491059507,0,ad2cf281,3164777808">看弹幕半夜笑出声</d><d p="187.15200,1,25,16777215,1491059510,0,ad2cf281,3164786076">就迷这个喘息声</d><d p="45.72900,1,25,16777215,1491159786,0,7737d340,3170178676">貌似</d><d p="203.06100,1,25,16777215,1491210300,0,be319717,3172693128">好舒虎</d><d p="196.44000,1,25,16777215,1491224973,0,ad2cf281,3174619056">好困</d><d p="95.78100,5,25,11890,1491318670,0,946187db,3182344438">放屁 to you</d><d p="95.78100,5,25,14811775,1491318671,0,946187db,3182345736">放屁 to you</d><d p="95.78100,5,25,41194,1491318672,0,946187db,3182346796">放屁 to you</d><d p="95.78100,5,25,38979,1491318670,0,946187db,3182347894">放屁 to you</d><d p="95.78100,5,25,16707842,1491318672,0,946187db,3182349004">放屁 to you</d><d p="95.78100,5,25,15138834,1491318672,0,946187db,3182350350">放屁 to you</d><d p="253.02700,4,25,15138834,1491318674,0,946187db,3182366152">越到后面吐字越清楚了 没刚开始那么爽啦</d><d p="9.50100,5,25,15138834,1491322324,0,8e4088c5,3182596246">记住这张纸</d><d p="46.59200,4,25,16707842,1491322325,0,8e4088c5,3182600728">very quiet</d><d p="92.38400,4,25,16707842,1491322327,0,8e4088c5,3182604990">from ear to ear</d><d p="112.97700,4,25,16707842,1491322326,0,8e4088c5,3182607778">we want</d><d p="119.19600,4,25,16707842,1491322328,0,8e4088c5,3182609228">back to a little xxoo</d><d p="157.31600,4,25,16707842,1491322329,0,8e4088c5,3182613636">that's what i always do to u</d><d p="207.83600,4,25,16707842,1491322330,0,8e4088c5,3182617508">先酝酿一下屁</d><d p="170.38500,1,25,16777215,1491498089,0,665377d3,3191772610">听了快三分钟发现没插耳机。。。还是爽，没救了</d><d p="102.28200,1,25,16777215,1491563247,0,b7fb78be,3194520632">说放屁的严肃点 我都笑精神了</d><d p="31.18200,1,25,16707842,1491674530,0,adc2524a,3202011128">见叔困</d><d p="103.04600,1,25,16777215,1491674564,0,4a6c5a6a,3202087200">放屁的尼玛！！！</d><d p="306.05900,1,25,16777215,1491750662,0,e7f1e6a3,3206646106">6</d><d p="20.74600,1,25,16777215,1491933771,0,f4199553,3214533968">立，又，透，朽，开，进，妹子，塞伊，QQ牛里脊有</d><d p="977.22200,1,25,16777215,1492009911,0,171630c3,3217603422">可能都睡着了</d><d p="263.63900,1,25,16777215,1492106528,0,b0805556,3221169228">我是尾巴骨痒</d><d p="321.80400,1,25,16777215,1492192965,0,89b627b3,3225224760">已撸</d><d p="31.27100,1,25,16777215,1492344536,0,ac0abf51,3234101156">卧槽</d><d p="138.10500,1,25,0,1492384074,0,8846575a,3235637144">真怕突然来一个喷嚏</d><d p="115.23600,1,25,0,1492531955,0,b219ebbb,3241923546">放屁的笑出声  有毒</d><d p="610.36500,1,25,0,1493193887,0,2d38aebc,3273249660">哇困了</d><d p="128.03100,1,25,0,1493219499,0,231c0683,3275028336">笑死</d><d p="157.55500,1,25,0,1493409870,0,be4e620a,3283274666">给你一些不同的屁12</d><d p="254.86100,1,25,16777215,1493409871,0,be4e620a,3283275818">喔ruai</d><d p="295.34100,1,25,16777215,1493409872,0,be4e620a,3283276384">嗯？我回来了</d><d p="102.88600,1,25,0,1493571671,0,f1f9c45d,3294660792">哈哈哈哈哈</d><d p="126.51000,1,25,0,1493957548,0,d70c2f56,3313070616">英语听力满分？？</d><d p="314.59400,1,25,16777215,1494003669,0,af908016,3316569714">同硬</d><d p="99.98900,1,25,16777215,1494140590,0,9d80152,3325127570">放屁to you 哈哈哈哈哈你们有毒救命啊让我睡觉</d><d p="236.76100,1,25,0,1494166239,0,b400c8a7,3327554276">怎么听清的…</d><d p="33.83900,1,25,16777215,1494425444,0,462b5831,3338650598">几乎听不到的声音？翻译过来</d><d p="373.61600,1,25,0,1494515493,0,af46824,3342571318">啊叔摸我头了</d><d p="355.00900,1,25,16777215,1494558706,0,3bb40dbb,3343701394">有口臭哈哈哈</d><d p="55.94900,1,25,0,1494601888,0,43b33f3,3346881904">见叔困</d><d p="52.02100,1,25,16777215,1494612121,0,c5e601fb,3347465242">见叔困</d><d p="52.91200,1,25,16777215,1494702183,0,f8e14679,3353163406">我只是听，看是辣眼睛</d><d p="115.35000,1,25,16777215,1494771053,0,438c6663,3358099172">FA</d><d p="79.41100,1,25,16777215,1494861092,0,64d87029,3362126644">诶呦我的腰。。。</d><d p="110.52600,1,25,16777215,1494861092,0,64d87029,3362130192">笑醒了。。。。</d><d p="659.88500,1,25,16777215,1494896993,0,cbcde854,3362958662">不知为嘛听着有种莫名的焦躁……</d><d p="182.25400,1,25,0,1494951179,0,f833ed94,3366128392">为什么这么大底噪是搬运问题吗</d><d p="211.69400,4,25,15138834,1495123960,0,e072c44a,3373118177">What are you talking about</d><d p="232.19700,4,25,15138834,1495123960,0,e072c44a,3373119897">I really don't know what you're talking about</d><d p="12.70000,1,25,0,1495130564,0,3348f261,3373343769">德叔的手法很好啊啊啊</d><d p="158.90000,1,25,16777215,1495137849,0,cb234e10,3373409603">我为什么要开着德叔复习....作死</d><d p="193.00400,1,25,15138834,1495203055,0,1b7b8060,3376920811">弹幕还让不让人睡</d><d p="691.59900,1,25,16777215,1495224256,0,3cdb5c44,3377861903">德罗本</d><d p="4.40900,1,25,0,1495256474,0,1c94cfbd,3379243473">来跟着我画就能抽SSR</d><d p="86.81000,1,25,0,1495274780,0,cbc2140e,3380670247">前方高能</d><d p="91.50800,1,25,15138834,1495274781,0,cbc2140e,3380677849">前方高能!</d><d p="339.78400,1,25,16777215,1495285796,0,cb7d887b,3381909377">1</d><d p="408.06000,1,25,16777215,1495285797,0,cb7d887b,3381919139">硬算什么，有本事你撸一个←_←</d><d p="34.62300,1,25,16777215,1495336268,0,59a811b0,3384501257">为什么我听一点底噪都没有</d><d p="66.70900,1,25,16777215,1495357500,0,d7b552c6,3386506925">添耳？？？</d><d p="187.52300,1,25,16777215,1495379462,0,415cfdb7,3388672017">科比</d><d p="43.99900,1,25,16777215,1495379515,0,3093e2d1,3388974195">asmr难道系统化了？健全了？分专业不专业了么</d><d p="106.39000,1,25,0,1495469525,0,93b79750,3393342505">？？？？？？？？弹幕</d><d p="484.23400,1,25,0,1495469547,0,79a5587d,3393428031">我靠差点睡着</d><d p="192.88900,1,25,16777215,1495519331,0,2fac7d97,3394797545">可以去听敲击狂魔的，他的也不错</d><d p="422.78100,1,25,16777215,1495725115,0,ce04d683,3404784166">都睡着了？</d><d p="126.52000,1,25,16777215,1495897865,0,ff401b6f,3409933416">见德困</d><d p="149.12800,1,25,0,1495901528,0,601c919b,3410123522">英语听力。</d><d p="106.83300,1,25,16777215,1495901537,0,bb3d9252,3410147301">建议关弹幕否则你会笑得睡不着觉哈哈哈哈哈</d><d p="96.56900,1,25,16777215,1495973318,0,2ffc60be,3412499962">good</d><d p="40.16200,1,25,16707842,1495994522,0,fd2f09b8,3413438286">一只大天狗</d><d p="48.14000,1,25,16707842,1495994520,0,fd2f09b8,3413438704">一只妖刀姬</d><d p="50.76200,1,25,16707842,1495994520,0,fd2f09b8,3413439011">一只阎魔</d><d p="54.86100,1,25,16707842,1495994520,0,fd2f09b8,3413439320">一只两面佛</d><d p="72.04100,1,25,16707842,1495994523,0,fd2f09b8,3413440220">德叔说下次表演抽酒吞</d><d p="415.86900,1,25,0,1495994543,0,5da43004,3413463302">都睡吧你们别撑着了</d><d p="462.07200,1,25,16777215,1496067032,0,835d2b48,3416231672">德叔抬头的那一瞬间我以为是普京</d><d p="95.47600,1,25,0,1496070711,0,9b633801,3416535269">放屁啊</d><d p="92.06500,4,25,16777215,1496070711,0,9b633801,3416537082">放屁呀</d><d p="23.82100,1,25,16777215,1496074327,0,a8c2dd00,3416591221">他写的是英文？</d><d p="23.10100,1,25,16777215,1496074360,0,8e2dcbfc,3416689697">神棍的</d><d p="343.07800,1,25,16777215,1496074373,0,8e2dcbfc,3416721511">1</d><d p="3.17900,1,25,16777215,1496080958,0,c7a0407f,3416897747">。</d><d p="344.03600,1,25,0,1496113895,0,6fcb6f65,3417577494">1</d><d p="362.18300,1,25,0,1496120467,0,4df93a73,3417858523">这干啥呢</d><d p="362.18300,1,25,0,1496120467,0,4df93a73,3417858941">没感觉啊</d><d p="444.89800,1,25,0,1496120469,0,4df93a73,3417864825">盯着后面的那副画，会有动的感觉</d><d p="652.34800,1,25,0,1496120473,0,4df93a73,3417877006">德功力不足啊叔</d><d p="700.25500,1,25,0,1496120473,0,4df93a73,3417879736">妈的，被影响心率了</d><d p="56.98100,1,25,16777215,1496138764,0,8d2b14d2,3418755975">罗夏！</d><d p="284.86200,1,25,14811775,1496160757,0,7c20a4fe,3419918595">好困呐</d><d p="62.63300,1,25,16777215,1496160777,0,a835d3e5,3419951900">是有点像罗夏</d><d p="151.62800,1,25,16777215,1496243479,0,f642b5bd,3421951202">熊叔？做实验的那个？</d><d p="170.59400,1,25,0,1496322543,0,28ca830d,3423651502">爽！</d><d p="136.86000,1,25,16777215,1496340150,0,732ad73a,3424357781">考验英语听力的时候到了</d><d p="298.34100,1,25,16777215,1496340153,0,732ad73a,3424359641">这个光线好催眠</d><d p="100.67700,1,25,0,1496419978,0,acaa3513,3426608700">翻译真厉害</d><d p="140.42900,1,25,0,1496419978,0,acaa3513,3426609870">翻译听力满分</d><d p="331.00100,1,25,16777215,1496426520,0,285c2b8,3426700457">2017 6 3</d><d p="160.49600,1,25,16777215,1496589086,0,21358beb,3431937999">还是德叔牛逼</d><d p="103.07700,1,25,0,1496589108,0,723d0835,3431990436">放弃的泥垢…</d><d p="116.14900,1,25,0,1496589108,0,723d0835,3431990997">放屁的笑出声…</d><d p="138.36800,5,25,16707842,1496679167,0,6beac0dd,3434388757">[‡‡‡‡‡‡‡‡‡‡‡‡‡‡顶灯‡‡‡‡‡‡‡‡‡‡‡‡‡‡‡]</d><d p="137.37100,5,25,15138834,1496679168,0,6beac0dd,3434390980">完蛋了，我要说什么，想不起来了</d><d p="137.45000,4,25,16707842,1496679171,0,6beac0dd,3434395249">↑哇，好大的顶灯呀！↑</d><d p="268.50700,1,25,0,1496761909,0,850bc0ac,3436822829">没啊，明明也很舒服</d><d p="0.09200,1,25,16777215,1496844649,0,ad168a3b,3439287954">第一</d><d p="172.29200,1,25,16707842,1496880482,0,34c75268,3439863237">boy♂next♂door</d><d p="349.99400,1,25,16777215,1496927347,0,2182915c,3441484328">天啦撸好困啊</d><d p="8.65200,1,25,0,1496938364,0,1e297971,3442103219">见叔困</d><d p="319.94400,1,25,16777215,1497006467,0,c4e81d5e,3443814653">跟心态没有关系</d><d p="273.34700,1,25,16777215,1497017408,0,73a6b1a4,3444257105">第一次听asmr都会觉得痒。</d><d p="22.82100,1,25,16777215,1497024739,0,12c97f9a,3444685099">好像第一次看见男的哦，哈哈先看看</d><d p="344.03600,1,25,16777215,1497276615,0,41739f00,3453212383">1</d><d p="84.82300,1,25,0,1497276623,0,850bc0ac,3453237291">我的腰。。。</d><d p="102.04400,1,25,16777215,1497366693,0,20e42710,3455887943">哈哈哈哈哈</d><d p="69.63200,1,25,0,1497459697,0,c60f50ca,3458568316">男</d><d p="515.56500,1,25,16777215,1497885065,0,c09fc0c9,3473154539">在撸</d><d p="37.15100,1,25,16777215,1497888762,0,531db7d3,3473478562">almost inaudible</d><d p="106.35500,1,25,16777215,1497967821,0,9e9271e6,3475964852">哈哈哈哈哈哈空耳</d><d p="237.40000,4,25,15138834,1497971479,0,df6d204a,3476173622">下方字幕满分</d><d p="23.77600,1,25,0,1497978066,0,50e1824b,3476453945">神秘</d><d p="47.81400,1,25,0,1497978066,0,50e1824b,3476454653">徳叔的声音有魔力</d><d p="398.36300,1,25,16777215,1498057888,0,e292031,3479202858">2017.6.21</d><d p="428.63800,1,25,16777215,1498197758,0,69376385,3483540832">越到后面弹幕越少。(๑•ั็ω•็ั๑)</d><d p="611.45500,1,25,16777215,1498197761,0,69376385,3483548570">幸存者2号。。</d><d p="849.34500,1,25,16777215,1498280498,0,ed7c9f4e,3486538813">木吉</d><d p="47.74600,1,25,16777215,1498323692,0,6bb43399,3488866385">德叔变得好瘦</d><d p="257.62200,4,25,15772458,1498338337,0,ee7868af,3489111324">around you</d><d p="550.59700,1,25,16777215,1498489917,0,511c8376,3495127699">唯一见过的不带耳机的</d><d p="98.83200,1,25,16777215,1498539688,0,2a0b8cb3,3496209307">放屁to you 笑醒了我</d><d p="118.65100,1,25,16777215,1498666375,0,cee964db,3501266709">用入耳式耳机好爽</d><d p="84.77500,1,25,16777215,1498745452,0,212e744e,3503868464">后腰痒的憋走！加我一个</d><d p="672.55600,1,25,16777215,1498795954,0,4244e1ad,3505159390">在看着德叔发动麒麟臂</d><d p="141.60200,1,25,0,1498986302,0,c1facbe6,3513412688">暴屁不止</d><d p="273.80900,1,25,16777215,1499004659,0,51b83b9e,3514754000">，弹幕一群逗比</d><d p="281.62200,1,25,16777215,1499184775,0,9ddf173c,3522068237">手机都拿不住了</d><d p="38.50100,4,25,16777215,1499350217,0,b94dbe07,3528754018">我爱你</d><d p="305.66700,1,25,16777215,1499421975,0,9381521c,3531503707">前面说腰好痒的别走</d><d p="300.33100,1,25,16777215,1499429320,0,3dd9fc31,3532024674">6</d><d p="122.68100,1,25,0,1499440277,0,2c0acfc3,3532660004">你们真烦人！哈哈哈哈哈！！</d><d p="229.55600,1,25,0,1499440278,0,8cf7e4f0,3532664634">男的</d><d p="343.56200,1,25,0,1499440279,0,8cf7e4f0,3532670037">1</d><d p="290.52800,1,25,16777215,1499446915,0,1e6a9dba,3533101437">晚安</d><d p="111.81800,1,25,0,1499454202,0,d70c2f56,3533196036">用力把你掰弯</d><d p="339.22200,1,25,16777215,1499457857,0,f91b0ce5,3533229516">口臭的别跑。立马破功</d><d p="261.29400,5,25,16777215,1499526695,0,ee6225de,3536448291">基佬fang pi</d><d p="288.22800,4,25,16777215,1499526696,0,ee6225de,3536450785">基佬放屁</d><d p="534.50400,1,25,16777215,1499619675,0,46ff7813,3540610060">是啊</d><d p="583.28700,1,25,16777215,1499619676,0,46ff7813,3540611729">德叔脸上有个豆豆 想捏爆</d><d p="35.10800,1,25,16777215,1499619695,0,310e870a,3540650252">inaudible</d><d p="346.30000,1,25,16777215,1499623335,0,7cf805a7,3540708963">1</d><d p="107.74000,1,25,16777215,1499630697,0,97f29fb4,3540821933">弹幕有毒哈哈哈哈毫无睡意</d><d p="172.27900,1,25,15138834,1499695834,0,8a22f256,3543933295">戏命师配音员</d><d p="102.07500,1,25,38979,1499706073,0,2905b0d1,3544531787">哈哈哈哈弹幕够了，让不让人睡呀</d><d p="37.82400,4,25,15138834,1499835684,0,d9c27162,3549720448">吻我</d><d p="107.62400,4,25,14811775,1499835687,0,d9c27162,3549726499">我一个女的硬了</d><d p="864.86700,1,25,16777215,1499839378,0,4e0557bf,3550081266">人呢</d><d p="4.20100,1,25,15138834,1499878899,0,1f7f7daf,3552306515">德叔的居然有底噪？</d><d p="3.27200,1,25,16777215,1499962338,0,14b77a81,3556042069">好久没看了</d><d p="146.09900,5,25,41194,1500048723,0,514a272a,3559869295">好红红火火恍恍惚惚完蛋那个笑醒</d><d p="521.71100,1,25,15138834,1500048726,0,514a272a,3559879337">在撸那个什么心态..？</d><d p="160.35500,1,25,16777215,1500048747,0,26433ccc,3559942922">这才是ASMR</d><d p="170.27300,1,25,16777215,1500051711,0,4590b505,3560138484">qiz</d><d p="172.15400,1,25,16777215,1500051711,0,4590b505,3560139558">齊祖</d><d p="457.13700,1,25,16777215,1500098526,0,17bd1,3561513930">我一个女的 竟然湿了</d><d p="99.52200,1,25,15772458,1500109511,0,9c529b11,3562193048">腰软了</d><d p="711.06800,1,25,16777215,1500145434,0,22f207bd,3564311088">听不懂……</d><d p="397.31500,1,25,0,1500448383,0,2fdb4013,3577668473">硬了</d><d p="20.66700,1,25,0,1500487748,0,4ba25843,3580103501">叔</d><d p="245.89400,1,25,16777215,1500490284,0,6b89b9ef,3580153452">应该叫德克士</d><d p="308.48100,1,25,16777215,1500490329,0,6b89b9ef,3580154454">奥义♂很爽</d><d p="17.17600,1,25,0,1500528580,0,8cf7e4f0,3581391143">我喜欢大叔该怎么办，</d><d p="65.76500,1,25,0,1500528658,0,8cf7e4f0,3581395060">男生举手</d><d p="148.97700,1,25,0,1500528725,0,8cf7e4f0,3581400438">我得关上弹幕了，不行了(▼皿▼#)</d><d p="509.09000,1,25,15138834,1500552030,0,3709df49,3582962343">。</d><d p="515.40900,1,25,38979,1500552044,0,3709df49,3582963250">绿了</d><d p="257.92000,1,25,16777215,1500568462,0,14bc8da7,3584089193">我的天我的天我的腰撑不住了</d><d p="629.01200,1,18,16777215,1500582797,0,597bf836,3584406826">这是在干嘛 没感觉啊</d><d p="205.37900,1,25,16777215,1500662187,0,f793697a,3588469812">有底噪的可以换耳机了</d><d p="84.59200,1,25,0,1500662880,0,515e6ab,3588483215">d</d><d p="341.30700,1,25,16777215,1500783097,0,d1791a2f,3593651453">2</d><d p="331.38600,1,25,16777215,1500813337,0,6f45f0eb,3595652532">德叔我爱你</d><d p="159.95900,1,25,16777215,1500832642,0,732ab1f4,3596874990">看弹幕笑喷</d><d p="9.12300,1,25,16777215,1500835090,0,efc556a5,3596932962">见叔滚</d><d p="157.28600,4,25,16777215,1500909940,0,bc54c07b,3600674043">mean to you?</d><d p="269.33800,4,25,16777215,1500910080,0,bc54c07b,3600683833">this moment</d><d p="175.91400,1,25,16777215,1500915101,0,18a3597,3600968260">接下来给大家带来一段bbox希望大家喜欢</d><d p="57.83800,1,25,16777215,1500915675,0,ef1915da,3600989842">手跟着一起动</d><d p="120.16100,1,25,16777215,1500917450,0,bfeed47a,3601056038">字幕老哥能不能顺便翻译一下。。。</d><d p="447.53800,1,25,16777215,1500991079,0,44b0e79,3604524415">啪，手机砸脸上</d><d p="75.38500,1,25,16777215,1500996081,0,ff9b2b35,3604957663">男</d><d p="149.69800,1,25,16777215,1501009505,0,dd815146,3605522879">好困</d><d p="230.49900,1,25,16777215,1501009586,0,dd815146,3605524104">如果在帅点 怕是要跟手机谈恋爱了</d><d p="90.54100,1,25,16777215,1501056019,0,9a24d53e,3607397332">男生＋1</d><d p="127.13300,1,25,16777215,1501085558,0,ea2c698e,3609590588">弹幕有毒！！</d><d p="143.89700,1,25,16777215,1501085557,0,ea2c698e,3609591572">这弹幕有毒。</d><d p="151.77300,1,25,16777215,1501085564,0,ea2c698e,3609592059">还让不让人睡了。</d><d p="113.80500,1,25,9599289,1501085597,0,939b8117,3609592827">哈哈哈笑精神</d><d p="1035.22400,1,25,0,1501135999,0,3588bfcb,3611505533">刚刚睡着了，又被吵醒了ᕦ(ò_óˇ)ᕤ“</d><d p="1042.30100,1,25,0,1501136006,0,3588bfcb,3611506027">????????????</d><d p="100.03000,1,25,16777215,1501187430,0,b32a7fef,3614518061">弹幕给我笑醒</d><d p="97.01100,5,25,16777215,1501210586,0,c133130e,3615139925">放屁 to you</d><d p="98.21900,1,25,16777215,1501226128,0,80159529,3616267488">哈哈哈</d><d p="426.92900,1,25,16777215,1501263809,0,5eb61093,3618881159">1945.8.15</d><d p="348.01000,1,25,16777215,1501351138,0,4590b505,3623421927">1</d><d p="318.08800,1,25,16777215,1501352661,0,f3afc1bc,3623466584">现在有人吗，有的扣个1</d><d p="133.94300,1,18,16777215,1501474913,0,4fd8b17d,3629134049">We want ……papapapapa?</d><d p="307.70100,1,25,16777215,1501488628,0,9d7526a8,3630133070">6</d><d p="422.81000,1,25,16777215,1501488695,0,9d7526a8,3630139639">2008.1.28</d><d p="91.81800,1,25,16777215,1501510939,0,ddcc6ce7,3631812973">难道德叔要舔耳</d><d p="7.59000,1,25,6830715,1501581114,0,1faea1f7,3635150609">啦啦啦</d><d p="218.74900,1,25,16777215,1501601807,0,906c7cbc,3636827929">surge粉安利</d><d p="48.17800,1,25,16777215,1501604044,0,eaf5e6f8,3636983369">想看德叔舔耳</d><d p="111.38300,1,25,16777215,1501604144,0,eaf5e6f8,3636989218">想看德叔舔耳！！想看德叔舔耳！！</d><d p="390.89800,1,25,16777215,1501643651,0,7ccf2263,3638103404">呼吸声听的好困</d><d p="105.40700,1,25,15138834,1501694685,0,17a41eeb,3641850622">厉害了，这听力</d><d p="279.06800,1,25,0,1501707767,0,a758f076,3642114112">#后台模式</d><d p="289.33800,1,25,0,1501707778,0,a758f076,3642114187">#后台播放</d><d p="78.21900,1,25,16777215,1501730232,0,9d3c17af,3642845647">哈哈哈哈哈哈</d><d p="86.78300,1,25,16777215,1501730240,0,9d3c17af,3642846170">字幕君么么哒</d><d p="97.43800,1,25,16777215,1501730233,0,9d3c17af,3642846862">哈哈哈哈哈哈</d><d p="1.54000,1,25,16777215,1501778981,0,62737d92,3646516892">我是世界第几帅</d><d p="110.45900,1,25,16777215,1501866644,0,23c644b1,3651253069">笑一笑精神了。。。</d><d p="251.30700,1,25,16777215,1501949223,0,aeaeaf31,3655590417">德叔原名：德莱文</d><d p="336.38000,1,25,16777215,1502040657,0,6b19d7be,3660423534">2017.8.7</d><d p="477.85000,1,25,15138834,1502121342,0,9def673c,3664692602">普京 伊涅斯塔 罗本哈哈哈</d><d p="406.26000,1,25,16777215,1502203483,0,68499a42,3668720281">20170808</d><d p="614.50000,1,25,16777215,1502203594,0,68499a42,3668738967">33333</d><d p="847.03800,1,25,16777215,1502203841,0,68499a42,3668761081">人</d><d p="325.75200,4,25,16777215,1502206624,0,864b2267,3668980419">底部蜜汁空耳</d><d p="9.47300,1,25,16777215,1502212911,0,d63f676c,3669332781">o</d><d p="976.70900,1,25,16777215,1502260089,0,68499a42,3671086599">都睡了????</d><d p="1082.50600,1,25,16777215,1502260170,0,68499a42,3671092022">困了(இдஇ; )</d><d p="69.59100,1,25,16777215,1502295524,0,63c94012,3673747300">用手指竟然不能在上面写字</d><d p="329.06200,1,25,16777215,1502295856,0,63c94012,3673766905">哈哈</d><d p="14.89000,1,25,16777215,1502354877,0,14467a3a,3676446145">收藏6666</d><d p="340.23900,1,25,38979,1502360795,0,6822bca2,3676856356">1</d><d p="71.61300,1,25,16777215,1502389622,0,a7152926,3678850292">来放屁啊</d><d p="75.91300,1,18,41194,1502389669,0,a7152926,3678851434">来放屁啊～</d><d p="508.32200,1,25,16777215,1502408817,0,b2d226f4,3679119682">不知道为啥听到他的声音好难受。。。</d><d p="149.97700,1,25,16777215,1502509368,0,6b2e1238,3684563885">你们有毒啦听个asmr被弹幕活活笑醒</d><d p="2.32100,5,25,16777215,1502509424,0,6b2e1238,3684568878">前排提醒，想睡觉的最好关上弹幕。不然………………</d><d p="28.45400,1,25,16777215,1502546999,0,88c0df7c,3687352235">三两汁</d><d p="93.15800,1,25,16777215,1502559959,0,23cdc1b8,3688299126">爱棒</d><d p="111.23700,1,25,16777215,1502559977,0,23cdc1b8,3688299834">夹死棒</d><d p="127.45500,1,25,16777215,1502559993,0,23cdc1b8,3688300418">萎王</d><d p="144.21900,1,25,16777215,1502560010,0,23cdc1b8,3688301061">三顶</d><d p="163.05400,1,25,16777215,1502560010,0,23cdc1b8,3688301731">咪头 耶～</d><d p="187.96200,1,25,16777215,1502560053,0,23cdc1b8,3688302644">deep♂</d><d p="63.08300,1,25,16777215,1502640204,0,22a902ea,3692693462">只有我一个人毫无感觉吗</d><d p="164.10700,1,25,16777215,1502724812,0,afa3662e,3697275218">突然发现 看过</d><d p="329.48400,1,25,16777215,1502814551,0,1308ee65,3702263163">1</d><d p="368.84100,1,25,16777215,1502814676,0,1308ee65,3702265597">6</d><d p="303.87600,1,25,16777215,1502905991,0,4c1b63b0,3707149920">6</d><d p="463.31700,1,25,16777215,1502913866,0,77aa0b85,3707313240">他吹气有凉爽的感觉！</d><d p="69.34100,1,25,16777215,1502980219,0,2f8c9cfc,3711067530">德邦总管</d><d p="88.52900,1,25,16777215,1502984045,0,5fa35b33,3711366661">哈哈哈哈黄字</d><d p="83.53900,1,25,16777215,1503076452,0,d1d7a423,3716397792">。？？？</d><d p="40.19900,5,25,16777215,1503081312,0,3991cb2c,3716562675">试试能不能发顶部弹幕</d><d p="21.28900,1,25,16777215,1503081531,0,3991cb2c,3716568876">试试顶部弹幕</d><d p="23.81000,5,25,16777215,1503081576,0,3991cb2c,3716569108">弹幕</d><d p="920.82500,1,25,16777215,1503173315,0,2c6986eb,3721408989">纸板子睡不着了</d><d p="312.37600,1,25,15138834,1503210908,0,5ade67f,3723053920">嘛，现在有人在看吗 有的扣1！</d><d p="338.21900,1,25,15138834,1503210941,0,5ade67f,3723056344">2017.8.20.</d><d p="342.23700,1,25,15138834,1503210850,0,5ade67f,3723057437">2017.8.20 14:35</d><d p="323.86600,1,25,16777215,1503327835,0,24d7f048,3729973927">1</d><d p="432.17100,1,25,16777215,1503329207,0,8ebb0161,3730073491">啊――贼诱不知道为啥</d><d p="96.49600,1,25,16777215,1503342959,0,ea52969a,3730665900">郭敬明直男</d><d p="0.30000,5,25,15138834,1503345804,0,ad653037,3730708916">底躁是压制是出来的，</d><d p="85.71900,1,25,16777215,1503422516,0,843a6023,3735333779">巴咔巴咔</d><d p="106.54000,1,25,16777215,1503422536,0,843a6023,3735334589">字幕笑死</d><d p="125.52500,1,25,16777215,1503422445,0,843a6023,3735335321">英语听力</d><d p="343.53600,1,25,16777215,1503425287,0,cc16130f,3735426729">1</d><d p="216.20100,1,25,16777215,1503515654,0,7b797168,3740265661">做asmr不带耳机我只服德叔</d><d p="299.69700,1,25,41194,1503575716,0,e593d5,3743347528">耳朵暖烘烘的，满足啊(*’ｰ’*)</d><d p="340.07700,1,25,41194,1503575746,0,e593d5,3743350966">2017.8.23</d><d p="16.62500,1,25,16777215,1503578146,0,421d1098,3743525283">每次画都贴歪</d><d p="805.90500,1,25,16777215,1503603182,0,c743840f,3744961728">没人了吗……</d><d p="728.35100,1,25,16777215,1503680704,0,45378150,3749262058">睡不着，难受╭(°A°`)╮</d><d p="348.10800,1,25,16777215,1503728809,0,a68be8bb,3751146861">2019  11  11前来考古</d><d p="68.22000,1,25,16777215,1503767046,0,2c0fd32f,3754115328">吧唧嘴</d><d p="203.85400,1,25,16777215,1503767229,0,2c0fd32f,3754125001">德叔的外形+设备，就算是不怎么上档次的口腔音也没问题</d><d p="890.71900,1,25,16777215,1503767920,0,2c0fd32f,3754159016">一个人在耳边不停的吧唧嘴，感觉不舒服</d><d p="35.94000,1,25,16777215,1503812012,0,c6c5b492,3755799360">见叔困</d><d p="308.54600,1,25,16777215,1503851661,0,b5fdf5ea,3758759418">朕的幻肢！</d><d p="847.51000,1,25,16777215,1503984199,0,34845af4,3764703098">嗯对</d><d p="152.58500,1,25,16777215,1504071327,0,e9a073ee,3769050658">看弹幕睡不着了</d><d p="667.32800,1,25,16777215,1504104648,0,66639488,3771311408">见叔困</d><d p="345.41200,1,25,16777215,1504116806,0,36db38e1,3771933986">1</d><d p="232.12500,1,25,16777215,1504190880,0,b9b4e103,3775078734">有人吗</d><d p="376.58500,1,25,16777215,1504191025,0,b9b4e103,3775087881">？</d><d p="401.08800,1,25,16777215,1504190925,0,b9b4e103,3775089352">有</d><d p="135.57800,1,25,16777215,1504191167,0,ed3574e6,3775104406">口臭的那个给我站住</d><d p="318.81500,1,25,16777215,1504202064,0,8cfcd3af,3775566627">小白你球不踢了 不训练了呀 跑来asmr</d><d p="109.57600,1,25,16777215,1504258382,0,e2f9c54b,3777024760">诶6</d><d p="46.14100,5,25,6830715,1504283585,0,928b54d5,3778571429">看底端弹幕笑出声</d><d p="92.22400,1,25,16777215,1504284032,0,fb7c3466,3778592440">想听德叔舔耳的+1</d><d p="289.43400,1,25,16777215,1504299812,0,830e0e25,3778884351">想打他</d><d p="697.38900,1,25,16777215,1504299855,0,830e0e25,3778884581">长得不行</d><d p="86.83200,1,25,16777215,1504373615,0,1bb93991,3782504075">拯救德叔发际线</d><d p="53.53900,1,25,16777215,1504379459,0,865278de,3782643122">太舒服了┗┃・ ■ ・┃┛</d><d p="90.85900,1,25,16777215,1504443811,0,cfcae037,3785253766">好爽！！</d><d p="1081.08700,1,25,16777215,1504444811,0,cfcae037,3785306503">还有人吗？</d><d p="178.14100,1,25,16777215,1504691418,0,c7be8cb,3791842338">他喊一嗓子我们就完了</d><d p="641.39400,1,25,16777215,1504779757,0,22cdaa60,3794064029">硬了，我可能要弯</d><d p="272.44600,5,25,41194,1504803121,0,adfc66de,3795035158">为什么我哪里都不痒？我莫不是废了？</d><d p="96.76200,5,25,16777215,1504893283,0,3991cb2c,3797531872">放屁  to  you</d><d p="100.26200,1,25,16777215,1504932671,0,aa1decce,3798388322">问题有人就喜欢听口水音啊</d><d p="171.82600,1,25,16777215,1504932782,0,aa1decce,3798394058">觉着模糊听不太清的声音反而很助眠啊</d><d p="333.01800,1,25,16777215,1504932968,0,aa1decce,3798403795">2017.9.9啦</d><d p="430.78200,1,25,16777215,1504933086,0,aa1decce,3798410174">前面1945的那个2333</d><d p="104.46200,1,25,16777215,1504953552,0,158d6f50,3799392599">我本来很困的，结果看弹幕看精神了</d><d p="107.39500,1,25,16777215,1505189174,0,738e541,3806415956">夹死他</d><d p="63.06000,1,25,16777215,1505321600,0,142a121d,3809941698">的输完</d><d p="66.46000,1,25,16777215,1505321612,0,142a121d,3809942040">德叔写的好</d><d p="262.84900,1,25,16777215,1505405360,0,41c71490,3811786919">底噪感人</d><d p="68.33800,1,25,16777215,1505412455,0,1dbd7f87,3811939042">女的</d><d p="506.24700,1,25,16777215,1505579537,0,1b640987,3817086261">神棍德</d><d p="40.20400,1,25,16777215,1505640781,0,b02e9028,3819045853">看我的胡子</d><d p="34.18100,1,25,16777215,1505663809,0,31ced72,3820067801">#后台模式</d><d p="22.01200,1,25,6830715,1505673251,0,942bee26,3820266006">基佬紫</d><d p="489.96500,1,25,16777215,1505751926,0,dbf3034f,3821997506">承包空屏</d><d p="150.40200,1,25,16777215,1505760167,0,1105e2a7,3822130629">字幕大佬</d><d p="53.50300,1,25,16777215,1505916169,0,bc553d2f,3825409546">啊啊啊啊啊好想睡觉</d><d p="337.96500,1,25,16777215,1505971233,0,5faedd12,3826380433">德叔我也爱你</d><d p="25.24700,1,25,16777215,1506146820,0,75a38e1f,3830789118">竟然手挺好看的。?!</d><d p="85.15300,1,25,0,1506189960,0,d4a7ed2b,3832829890">什么见叔困系列我就根本没感bshkslmdbgdkajshwvfsjskmsn</d><d p="613.48100,1,25,16777215,1506235287,0,61b9fb64,3834093411">还活着3</d><d p="341.25700,1,25,16777215,1506346430,0,98514b3f,3837164437">2017 9 25</d><d p="116.61400,1,25,16777215,1506347080,0,ac093118,3837193256">牛逼了</d><d p="160.98900,1,25,16777215,1506347103,0,ac093118,3837195089">笑死我 让我睡觉</d><d p="499.66700,5,18,16777215,1506355636,0,824f0b9b,3837583761">emmmmmm</d><d p="104.82500,1,25,16777215,1506449392,0,caa26b6,3839610088">为什么我有种想跟他睡觉的冲动</d><d p="659.33800,1,25,16777215,1506653344,0,66392dc2,3844497404">？y</d><d p="19.76200,1,25,16777215,1506786713,0,2e01f765,3848168977">#后台模式</d><d p="14.43200,1,25,16777215,1506814790,0,d3918098,3848594618">天灵灵，地灵灵</d><d p="107.52000,1,25,16777215,1506826743,0,e5dec0d7,3848980364">哈哈哈哈哈哈放屁toyou的够了哈哈哈哈笑醒</d><d p="352.82700,1,25,16777215,1506830029,0,b0f01326,3849118280">1</d><d p="319.69100,1,25,16777215,1506924621,0,827438be,3852723034">不扣滚</d><d p="80.76000,1,25,16777215,1506933307,0,eb3ab601,3853144341">女生表示只想看男声asmr</d><d p="40.06100,1,25,16707842,1506961828,0,3991cb2c,3854803301">蚂蚁</d><d p="40.04100,4,25,16707842,1506961833,0,3991cb2c,3854804367">蚂蚁</d><d p="43.86200,4,25,16707842,1506961877,0,3991cb2c,3854805586">猫儿死</d><d p="137.00500,1,25,16777215,1506961848,0,232aaf00,3854807234">z</d><d p="0.40800,4,25,204,1507043551,0,c0551e7,3858333161">见德硬</d><d p="190.26600,1,25,16777215,1507100924,0,a58ddd48,3860447891">c</d><d p="116.30100,1,25,16777215,1507140143,0,eaa7fd55,3862882144">突然兄贵♂</d><d p="11.65400,1,25,15138834,1507212411,0,2a5247e,3865999166">猜猜我在画什么</d><d p="84.63400,1,25,16777215,1507304239,0,3aba2194,3870396086">为什么我的后腰好痒？？</d><d p="685.13100,1,25,16777215,1507446696,0,3d325841,3876755160">md，睡着了，手机给我吓掉了</d><d p="428.44800,1,25,16777215,1507448884,0,3b93c5fc,3876859271">如小仙女般晃来晃去</d><d p="319.80100,1,25,16777215,1507557849,0,66b2b206,3880053763">1</d><d p="333.55900,1,25,16777215,1507557882,0,66b2b206,3880055477">2018 3 26</d><d p="347.14000,1,25,16777215,1507565046,0,1350608a,3880417132">2017 12 25</d><d p="404.37600,1,25,16777215,1507565429,0,1350608a,3880424696">2017 12 25</d><d p="628.99200,1,25,16777215,1507605591,0,875339df,3880870848">幸存者3号</d><d p="63.96900,1,25,16777215,1507828052,0,d5b44b68,3888937724">猪睾</d><d p="50.42100,1,25,16777215,1507908360,0,b7362d3b,3891039323">我帅不</d><d p="342.97700,1,25,16777215,1507982162,0,f425bb1c,3893412390">1</d><d p="351.38700,1,25,16777215,1507982099,0,f425bb1c,3893412879">1</d><d p="339.50100,1,25,16777215,1508072149,0,4eea01fa,3896990895">1</d><d p="110.68200,1,25,16777215,1508252130,0,42c8a7e3,3901677665">下面的我忍不住了</d><d p="56.42100,4,25,16777215,1508255126,0,af073a63,3901816089">233</d><d p="240.95000,4,25,15138834,1508255560,0,af073a63,3901824841">Oh mama be straight baby</d><d p="143.77700,1,25,16777215,1508261331,0,77d0fd05,3901972168">弯了弯了</d><d p="102.49400,1,25,16777215,1508392672,0,64562420,3904366253">xiao 死我了，</d><d p="51.23300,1,25,16777215,1508559491,0,420bd834,3908643443">我以为要舔耳了呢</d><d p="215.55800,1,25,16777215,1508559579,0,420bd834,3908651279">倒霉催</d><d p="132.87200,1,25,16777215,1508605491,0,2ad8bf34,3910999643">zzzzzz</d><d p="1.35400,1,25,16777215,1508766715,0,6769e35c,3915568387">见叔困</d><d p="76.42600,1,25,16777215,1508775493,0,ed4abd23,3915939814">从评论只有十几一直听到现在还有感觉</d><d p="137.27500,5,25,16777215,1508803852,0,f9b92b05,3916160922">ggg</d><d p="142.84800,4,25,16777215,1508803860,0,f9b92b05,3916160995">ggg</d><d p="162.43300,1,25,16777215,1508803880,0,f9b92b05,3916161138">我是来看看等级的</d><d p="166.67200,1,25,16777215,1508877710,0,ebb928f,3917893797">耳朵痒</d><d p="69.40500,1,25,16777215,1508947415,0,7fe2d22a,3919497868">终于找到一个没有嘤嘤嘤的房间了</d><d p="270.21600,1,25,16777215,1508947597,0,7fe2d22a,3919504251">德州电锯杀人叔</d><d p="124.64100,4,18,16707842,1508956739,0,6457bf31,3919666070">听惯德叔后我发现，有才华的男子即使秃顶我也觉得莫名帅</d><d p="174.88200,4,18,16707842,1508956823,0,6457bf31,3919666714">德叔老巢在哪？我要去偷设备</d><d p="193.32100,4,18,11890,1508956865,0,6457bf31,3919667031">偷偷承包</d><d p="325.40500,1,25,16777215,1509028377,0,d9414a87,3921069112">1</d><d p="6.19800,1,25,16777215,1509117877,0,8e5b1688,3923370568">吧。。</d><d p="88.57300,1,25,15138834,1509203720,0,f25b2da2,3926252623">我的腿…好像有点那啥…</d><d p="271.83800,1,25,14811775,1509203997,0,f25b2da2,3926263444">大腿痒…</d><d p="75.70600,1,25,16777215,1509373902,0,e0437fac,3931144423">真的有点困是什么回事</d><d p="50.52600,5,25,16777215,1509514952,0,24874642,3933854701">666</d><d p="63.06500,5,25,16777215,1509514893,0,24874642,3933855216">666</d><d p="151.69700,1,25,16777215,1509646298,0,d385ce10,3936983040">我耳朵酥了，不对，麻了</d><d p="43.96700,1,25,16777215,1509656294,0,180902ab,3937043004">哈哈哈弹幕真是够了</d><d p="572.40100,1,25,16777215,1509792434,0,f4b8ee44,3940948003">在图书馆快看睡着了</d><d p="296.84300,1,25,16777215,1509982308,0,5c47f447,3947060691">考试考好  高考考得超级厉害！！</d><d p="307.80300,1,25,16777215,1509982410,0,5c47f447,3947061372">考试加油！！</d><d p="79.34000,1,25,16777215,1509988516,0,545beec1,3947241045">23333</d><d p="100.99200,1,25,16777215,1510074433,0,804a4752,3949181509">哈哈哈哈哈哈哈</d><d p="353.75600,1,25,16777215,1510162232,0,12cf63ac,3951116169">12.25的你在逗我</d><d p="95.75800,4,25,16777215,1510248727,0,e2ebfa5,3953087337">perform</d><d p="125.20100,1,25,16777215,1510248764,0,e2ebfa5,3953087876">笑醒哈哈哈哈哈哈</d><d p="147.58500,4,25,16777215,1510248559,0,e2ebfa5,3953088397">something that</d><d p="154.83000,4,25,16777215,1510248815,0,e2ebfa5,3953088650">meeting u</d><d p="84.12100,1,25,16777215,1510337075,0,b2a60614,3955232002">皇帝的新纸</d><d p="986.38400,1,25,16777215,1510340891,0,6a1d1bd8,3955280769">都睡着了</d><d p="531.34200,1,25,16777215,1510346267,0,a9ccc48d,3955317345">、？？？？？？？？？？？</d><d p="557.75600,1,25,16777215,1510346294,0,a9ccc48d,3955317474">麻蛋，手撑着头差点睡着</d><d p="60.62800,1,25,16777215,1510426708,0,fcfd560f,3958090067">sounds from my mouth</d><d p="208.15900,1,25,15138834,1510583707,0,6cbf67d6,3962657531">德克萨斯.叔</d><d p="288.27500,1,25,16777215,1511025529,0,f57a122,3973838033">左屁股痒</d><d p="0.54400,1,25,16777215,1511108002,0,82c7a380,3976725609">有</d><d p="50.93200,1,25,16777215,1511109795,0,9e495048,3976783010">吻我那个 当场笑喷莫名笑点啊哈哈哈哈哈哈</d><d p="278.54600,1,25,16777215,1511136819,0,c782a462,3977002626">these movements of here are perfectly normal</d><d p="108.86900,4,18,16707842,1511238640,0,d6bea536,3979133298">你一个女的怎么硬</d><d p="78.87500,1,25,16777215,1511281779,0,bd68b4ee,3980481995">男的</d><d p="353.29000,1,25,16777215,1511547574,0,be092e1c,3986257992">星宿老仙，法力无边</d><d p="28.56200,1,25,16777215,1511640318,0,10a3d77d,3988880462">这是张天书</d><d p="41.60300,4,25,16777215,1511640342,0,10a3d77d,3988880616">憋说话！吻我</d><d p="62.34200,4,25,16777215,1511717273,0,6c144199,3991608212">写了啥玩意</d><d p="60.74800,1,25,16777215,1511794955,0,91136f1c,3993271937">德叔竟然有底躁了？？？</d><d p="255.06900,1,25,16777215,1511795112,0,91136f1c,3993279108">我要开始做法了</d><d p="122.79000,5,25,15138834,1511884453,0,65b8584e,3995341312">我一个女的下面顶起来了</d><d p="49.78500,1,25,16777215,1511891014,0,a053eaec,3995504789">一只兲</d><d p="69.90200,4,25,15138834,1512062314,0,2744eb12,4003723143">顶部弹幕不要带节奏！！！！不懂规矩</d><d p="505.55600,1,25,16777215,1512327379,0,f0826265,4012116690">6</d><d p="106.81100,1,25,16777215,1512401348,0,c9671894,4013986517">我的腰好痒</d><d p="3.90100,1,25,16777215,1512496710,0,7ca9995,4016267336">#后台播放</d><d p="156.34500,1,25,16777215,1512662092,0,6256a649,4020166882">呼吸声有毒 听得我腰子痒</d><d p="36.25800,1,25,16777215,1512894780,0,ec3b3dce,4026953334">你们看见了吗，我看见了</d><d p="273.34400,1,25,16777215,1512985489,0,e13ada4d,4029332305">是this movements，别不懂装懂</d><d p="127.26400,1,25,16777215,1513099865,0,749f547d,4032267472">我明明很清醒啊fhhfswghuvjikjhtfdfd</d><d p="494.22100,1,25,16777215,1513168721,0,f0159c01,4033489081">王一个女的真的非常非常喜欢德叔说话的声音</d><d p="69.01000,1,25,16777215,1513200444,0,e13ada4d,4034228883">说的是as always都聋了？</d><d p="348.62200,1,25,16777215,1513238663,0,f933cb49,4034829517">1</d><d p="642.47500,1,25,0,1513260660,0,ad470cff,4035579553">快进者一号</d><d p="482.28600,1,25,16777215,1513281927,0,36036fa8,4036101570">好的asmr是要手势的，催眠学的基础</d><d p="46.83200,5,25,16777215,1513353706,0,8e5c8ffe,4038007586">。</d><d p="563.55300,1,25,16777215,1513404335,0,986d3d18,4039071186">听一个男的在这轻言细语是有点奇怪，不过di</d><d p="490.77900,1,25,16777215,1513498314,0,8b138888,4042406817">哎哟不行一吹气就一抖</d><d p="514.08000,1,25,16777215,1513498337,0,8b138888,4042407806">腰麻</d><d p="512.45300,1,25,16777215,1513513137,0,413827cc,4043029277">emmm</d><d p="113.75100,1,25,16777215,1513522518,0,92c3c23f,4043471151">你走开我要看后面的画</d><d p="82.15700,1,25,16777215,1513599457,0,500dbdd7,4045021827">我想听笔写字的声音</d><d p="113.35200,1,25,16777215,1513599488,0,500dbdd7,4045023111">聪明的人才能听到说了什么</d><d p="157.25100,1,25,16777215,1513613739,0,59048c3a,4045615278">中考听说不是事QAQ</d><d p="199.90900,1,25,16777215,1513683053,0,83cfc731,4046737007">我能感觉的到呵出的热气</d><d p="59.33900,1,25,16777215,1513794988,0,50dcf4f2,4049401604">我会用十分细微的口腔音</d><d p="62.84100,4,25,16707842,1513795039,0,50dcf4f2,4049401898">我会用十分细微的口腔音</d><d p="74.38100,4,25,16707842,1513795064,0,50dcf4f2,4049402118">就像对着你说话</d><d p="123.77600,1,25,16777215,1513962809,0,4495a1cb,4053311141">#后台播放</d><d p="87.23100,1,25,16777215,1513970147,0,9ce74ceb,4053426342">社会我徳叔人狠话不多</d><d p="168.61000,1,25,16777215,1514011991,0,1ba4f79d,4054325132">见叔困？开玩笑！不存hjghdjdkfhgeg</d><d p="10.05200,4,25,16707842,1514037771,0,81dcb210,4055477899">我可以吃掉它</d><d p="19.82800,4,25,16707842,1514037791,0,81dcb210,4055479300">上面有很多的蛋白质</d><d p="33.31800,4,25,16707842,1514037830,0,81dcb210,4055481788">蛋 白 质</d><d p="37.50100,4,25,16707842,1514037544,0,81dcb210,4055483497">我吃掉白纸了</d><d p="131.12200,1,25,16777215,1514047384,0,ea0075bd,4055996395">哈哈哈伊涅斯塔+小马哥</d><d p="172.53500,1,25,16777215,1514047114,0,ea0075bd,4055998059">为啥都没感觉？？？</d><d p="211.13600,1,25,16777215,1514047928,0,30700105,4056018401">汉子路过</d><d p="290.52700,1,25,41194,1514047938,0,30700105,4056023342">哇……他说的我一句都听不懂</d><d p="116.49400,1,25,16777215,1514137376,0,d5b44b68,4058907511">we want 啪啪啪</d><d p="560.81600,1,25,16777215,1514138040,0,d5b44b68,4058913487">我叫李裕同，我丁丁小</d><d p="971.71800,1,25,16777215,1514509855,0,266ed8ed,4121007645">还有谁！</d><d p="991.87500,1,18,14811775,1514509901,0,266ed8ed,4121008263">卧槽还真有</d><d p="55.94500,1,25,16777215,1514561307,0,43c0ac4a,4139933463">quite是十分的意思ok？</d><d p="171.04800,1,25,16777215,1514575779,0,f55d3085,4140334464">卧槽我的腰</d><d p="196.72400,1,25,16777215,1514648769,0,bf2c7144,4143001224">耳朵麻麻的</d><d p="82.76100,1,25,16776960,1514696976,0,179a430d,4144230687">en ?</d><d p="93.51300,1,25,16776960,1514696986,0,179a430d,4144231215">en?</d><d p="45.24900,1,25,16777215,1514746072,0,1fc1ee4f,4146792447">asmr ont vioce？</d><d p="66.77600,1,25,16777215,1514795282,0,e13ada4d,4148438925">写了quite sounds</d><d p="24.05700,5,25,16777215,1514810163,0,c1fd77e6,4149158452">见德困</d><d p="206.07500,1,25,16777215,1514826071,0,d3b0e3da,4149941228">一点屁用都没有，完全睡不179+09+00/.。./+.:+~~，/./:，:+/</d><d p="69.07700,1,25,16777215,1514845477,0,38d5cf3d,4150133124">souda</d><d p="354.14200,1,25,16777215,1515076122,0,af9af1bd,4156396895">2018'1'4</d><d p="362.66900,1,25,16777215,1515084404,0,2c0fd32f,4156722859">原来德叔也搞口腔音</d><d p="84.96100,1,25,16777215,1515257682,0,f770ecb,4162105102">好痒！！！</d><d p="73.37400,1,25,16777215,1515264498,0,a336360f,4162315171">腰好痒的别跑 差点以为就我一人</d><d p="526.03700,1,25,16777215,1515467179,0,df26325e,4168039629">.</d><d p="543.97700,1,25,16777215,1515467197,0,df26325e,4168039951">除了德叔还有谁</d><d p="628.09800,1,25,16777215,1515467282,0,df26325e,4168041606">斗鱼有个 男的也不错</d><d p="59.25600,1,25,16777215,1515484759,0,c6bddfb,4168527815">辣眼睛的有毛病？</d><d p="55.22000,1,25,16777215,1515602102,0,f7030507,4171836686">还让不让人睡觉了 笑醒</d><d p="26.79800,1,25,16777215,1515739937,0,916c5779,4174715540">波耶波罗蜜</d><d p="17.22200,1,25,16777215,1515766405,0,d8f8457e,4175752971">见叔困</d><d p="26.19200,1,25,16777215,1515864452,0,d0a4b405,4179249182">这时候 德叔还没有彻底秃</d><d p="102.36000,1,25,16777215,1515885476,0,99c1fe98,4179490381">我喜欢你</d><d p="110.85000,1,25,16777215,1515885831,0,99c1fe98,4179490463">我喜欢你</d><d p="116.23400,1,25,16777215,1515885836,0,99c1fe98,4179490501">我喜欢你</d><d p="123.11400,1,25,16777215,1515885844,0,99c1fe98,4179490572">我喜欢你</d><d p="128.97700,1,25,16777215,1515885850,0,99c1fe98,4179490602">我喜欢你</d><d p="267.87200,1,25,16777215,1516036515,0,927858cb,4184507416">视觉系加听觉系的asmr</d><d p="90.46100,1,25,16777215,1516102581,0,f18958b9,4185878126">字幕贼厉害</d><d p="188.33400,1,25,16777215,1516118320,0,1ed83cb4,4186685694">头皮发麻质壁分离</d><d p="427.47700,1,25,16777215,1516299133,0,1115ccb8,4191597101">maye左腿痒</d><d p="74.30300,1,25,16777215,1516491184,0,6e2b160d,4197404935">前面quiet是十分的，你英语。。。。</d><d p="329.38500,1,25,16777215,1516549250,0,df23219a,4199817927">困的都硬了</d><d p="351.40100,1,25,16777215,1516560873,0,c8838b9d,4200141130">像在做法 哈哈</d><d p="123.90500,1,25,16777215,1516639546,0,e67ea2bf,4202556094">久违了</d><d p="266.80800,1,25,16777215,1516898474,0,5b253a37,4213672706">屏咚</d><d p="16.01200,1,25,16777215,1517032027,0,c64044cf,4217722639">。</d><d p="21.26900,1,25,16777215,1517116857,0,989290e6,4221107929">我画你猜</d><d p="28.14100,1,25,16777215,1517116870,0,989290e6,4221108677">我画你猜</d><d p="356.61800,1,25,16777215,1517152496,0,64da00d9,4223112864">喜欢德叔轻声说话的就我一个吗😂</d><d p="597.70300,1,25,16777215,1517175520,0,a0ba1f34,4223712744">只有我一个人注意那幅画了吗</d><d p="79.01500,1,25,11890,1517588007,0,b5669152,4248675516">ddf</d><d p="520.59100,1,25,16777215,1517749172,0,22c358ab,4254634584">？</d><d p="524.13300,1,25,16777215,1517749197,0,22c358ab,4254636262">弹幕呢？</d><d p="1016.34900,1,25,16777215,1518009752,0,96a657d,4271874713">因为很多打着ASMR的名义，实际上是卖弄风骚。。。</d><d p="347.22900,1,25,16777215,1518358205,0,f4ca2c4f,4288352099">1111</d><d p="131.77900,1,25,16711680,1518535378,0,315750be,4296103728">23333</d><d p="61.79700,1,25,16777215,1518552814,0,88f382e0,4296723644">quiet sound?</d><d p="117.27000,1,25,16777215,1518896925,0,50dcf4f2,4313185421">女的不能硬的那个，孤陋寡闻了吧～</d><d p="28.73900,1,25,16777215,1519053164,0,4f3f852b,4319692417">他写的是我们沾点芝麻酱就可以吃了</d><d p="89.80700,1,25,16777215,1519053213,0,4f3f852b,4319695945">下面的黄字够了</d><d p="227.94300,1,25,16777215,1519154775,0,a174f1c4,4325861933">！</d><d p="277.38200,1,25,16777215,1519409220,0,1379849d,4337388426">人群当中突然钻出一个光头</d><d p="226.12300,1,25,16777215,1519862450,0,b538b513,4353888994">#后台播放</d><d p="96.26100,1,25,16777215,1519884937,0,83a78478,4354638920">我腰痒啊</d><d p="271.51300,1,25,16777215,1519977307,0,1df3d0b8,4358133794">前面屁股痒的等等我</d><d p="164.53100,1,25,16777215,1520088832,0,67849527,4362852464">见德困 晚安</d><d p="132.51900,1,25,16777215,1520103608,0,94a8dabe,4363490776">睡醒了起床让自己头皮发麻系列</d><d p="193.95900,1,25,16777215,1520437940,0,2ef4e265,4372315017">所以，德州的德叔咯</d><d p="201.88000,1,25,16777215,1520603018,0,f0159c01,4375793442">来这刷老番茄？出门左转谢谢</d><d p="127.34100,1,25,41194,1520764768,0,9b51554a,4381116536">辣妹儿。。。法科儿。。。</d><d p="369.38300,1,25,16777215,1520785649,0,9b39e88f,4382024864">海草舞来报道</d><d p="31.35300,1,25,16777215,1520865475,0,33c10ef8,4383772290">哈哈哈哈哈哈哈哈哈哈哈哈哈哈哈哈哈</d><d p="319.99100,1,25,16777215,1520957472,0,6271cb3d,4385947669">我听得想打人……</d><d p="64.21100,1,25,16777215,1521051430,0,3db0d08f,4387938730">末日铁拳</d><d p="26.43100,1,25,16777215,1521397871,0,7e11377c,4397785870">石了志</d><d p="201.25900,1,25,16777215,1521492980,0,f7973e43,4399820710">呼吸声简直爽爆</d><d p="301.01500,5,25,14811775,1521882083,0,f0159c01,4409145245">这个就是听他说话的声音 不说话我们听什么？</d><d p="23.79700,1,25,16777215,1521990252,0,3efd67e0,4413354797">叔这次有底噪</d><d p="11.73000,1,25,16777215,1522168360,0,2045540f,4417708189">拔刀吧</d><d p="49.46200,1,25,16777215,1522282629,0,8a50e1d2,4419861942">李连杰</d><d p="289.55000,1,25,16777215,1522342405,0,d4d1cd73,4421557580">困了困了</d><d p="11.93300,4,25,16777215,1522533587,0,df3a9b97,4427101666">ASMR</d><d p="302.02600,1,25,16777215,1522591946,0,df9a27d5,4429362996">66</d><d p="91.53500,1,25,16777215,1522645981,0,d0a40e2,4430437788">写的是:我，秦始皇，打钱！！</d><d p="14.10200,1,25,16777215,1522768196,0,11121dda,4433523913">啊ԅ(¯﹃¯ԅ)</d><d p="248.47200,5,25,11890,1522776721,0,ce364460,4433849778">做法开始！！！</d><d p="28.47600,1,25,16777215,1522777475,0,79bff30d,4433863199">巨恶心这口水音</d></i>